[
  {
    "peak_id": "peak_1",
    "apex_time_table": 0.4569091136392049,
    "apex_time_recomputed": 0.3790268783597949,
    "start_time": 0.3790268783597949,
    "end_time": 0.5347913489186148,
    "table_confidence_percent": 4.6,
    "prominence": 5.219,
    "width_time": 0.15576447055881987,
    "width_samples": 30.0,
    "height": 5.219,
    "snr": 0.522,
    "peak_area": 0.005,
    "prominence_threshold": 50.91828774585579,
    "width_threshold_samples": 0,
    "height_threshold": 163.56611541897632,
    "snr_threshold": 0.7484238145508164,
    "area_threshold": 0.17955217405091117,
    "prominence_percent_above_threshold": -89.75024449751892,
    "width_percent_above_threshold": 2999999999999900.5,
    "height_percent_above_threshold": -96.80924133544929,
    "snr_percent_above_threshold": -30.253421944718557,
    "area_percent_above_threshold": -97.21529409129724,
    "feature_explanation": "This peak's prominence is 89.8% below threshold, width is 2999999999999900.5% above threshold, height is 96.8% below threshold, S/N is 30.3% below threshold, and area is 97.2% below threshold.",
    "counterfactual_explanation": "If prominence were 89.8% lower, or width were 2999999999999900.5% lower, or height were 96.8% lower, or S/N were 30.3% lower, or area were 97.2% lower, this peak would fail detection.",
    "hybrid_explanation": "prominence: 5.219 (-89.8% above threshold), width: 30.000 (2999999999999900.5% above threshold), height: 5.219 (-96.8% above threshold), S/N: 0.522 (-30.3% above threshold), area: 0.005 (-97.2% above threshold).",
    "weakest_constraint_explanation": "The limiting factor is area, which is only -97.2% above its threshold.",
    "confidence": 0.046,
    "confidence_explanation": "Confidence is based on the weakest margin: -97.2% above threshold (lower means less robust)."
  },
  {
    "peak_id": "peak_2",
    "apex_time_table": 1.1007355919489936,
    "apex_time_recomputed": 1.1007355919489936,
    "start_time": 1.0643905488186025,
    "end_time": 1.137080635079385,
    "table_confidence_percent": 50.2,
    "prominence": 291.8447686899895,
    "width_time": 0.07269008626078244,
    "width_samples": 14.41381233466521,
    "height": 291.8374669166782,
    "snr": 19.957502576634944,
    "peak_area": 9.796697050909291,
    "prominence_threshold": 50.91828774585579,
    "width_threshold_samples": 0,
    "height_threshold": 163.56611541897632,
    "snr_threshold": 0.7484238145508164,
    "area_threshold": 0.17955217405091117,
    "prominence_percent_above_threshold": 473.1629668040881,
    "width_percent_above_threshold": 1441381233466421.0,
    "height_percent_above_threshold": 78.42171416074378,
    "snr_percent_above_threshold": 2566.604427681513,
    "area_percent_above_threshold": 5356.184032687615,
    "feature_explanation": "This peak's prominence is 473.2% above threshold, width is 1441381233466421.0% above threshold, height is 78.4% above threshold, S/N is 2566.6% above threshold, and area is 5356.2% above threshold.",
    "counterfactual_explanation": "If prominence were 473.2% lower, or width were 1441381233466421.0% lower, or height were 78.4% lower, or S/N were 2566.6% lower, or area were 5356.2% lower, this peak would fail detection.",
    "hybrid_explanation": "prominence: 291.845 (473.2% above threshold), width: 14.414 (1441381233466421.0% above threshold), height: 291.837 (78.4% above threshold), S/N: 19.958 (2566.6% above threshold), area: 9.797 (5356.2% above threshold).",
    "weakest_constraint_explanation": "The limiting factor is height, which is only 78.4% above its threshold.",
    "confidence": 0.502,
    "confidence_explanation": "Confidence is based on the weakest margin: 78.4% above threshold (lower means less robust)."
  },
  {
    "peak_id": "peak_3",
    "apex_time_table": 1.853597199649956,
    "apex_time_recomputed": 1.853597199649956,
    "start_time": 1.630334791848981,
    "end_time": 2.0820517564695584,
    "table_confidence_percent": 78.0,
    "prominence": 290.72749111729263,
    "width_time": 0.4517169646205774,
    "width_samples": 86.61554370357538,
    "height": 291.29285038405703,
    "snr": 1.86029743737691,
    "peak_area": 59.613515126205094,
    "prominence_threshold": 50.91828774585579,
    "width_threshold_samples": 0,
    "height_threshold": 163.56611541897632,
    "snr_threshold": 0.7484238145508164,
    "area_threshold": 0.17955217405091117,
    "prominence_percent_above_threshold": 470.96871082620953,
    "width_percent_above_threshold": 8661554370357439.0,
    "height_percent_above_threshold": 78.08875000663025,
    "snr_percent_above_threshold": 148.56203145986336,
    "area_percent_above_threshold": 33101.221562097024,
    "feature_explanation": "This peak's prominence is 471.0% above threshold, width is 8661554370357439.0% above threshold, height is 78.1% above threshold, S/N is 148.6% above threshold, and area is 33101.2% above threshold.",
    "counterfactual_explanation": "If prominence were 471.0% lower, or width were 8661554370357439.0% lower, or height were 78.1% lower, or S/N were 148.6% lower, or area were 33101.2% lower, this peak would fail detection.",
    "hybrid_explanation": "prominence: 290.727 (471.0% above threshold), width: 86.616 (8661554370357439.0% above threshold), height: 291.293 (78.1% above threshold), S/N: 1.860 (148.6% above threshold), area: 59.614 (33101.2% above threshold).",
    "weakest_constraint_explanation": "The limiting factor is height, which is only 78.1% above its threshold.",
    "confidence": 0.78,
    "confidence_explanation": "Confidence is based on the weakest margin: 78.1% above threshold (lower means less robust)."
  },
  {
    "peak_id": "peak_4",
    "apex_time_table": 2.627227403425428,
    "apex_time_recomputed": 2.627227403425428,
    "start_time": 2.580498062257782,
    "end_time": 2.6687645955744466,
    "table_confidence_percent": 30.1,
    "prominence": 172.63431442184222,
    "width_time": 0.08826653331666456,
    "width_samples": 16.81267280684534,
    "height": 181.39966184609935,
    "snr": 19.090465610530902,
    "peak_area": 6.9460037173891145,
    "prominence_threshold": 50.91828774585579,
    "width_threshold_samples": 0,
    "height_threshold": 163.56611541897632,
    "snr_threshold": 0.7484238145508164,
    "area_threshold": 0.17955217405091117,
    "prominence_percent_above_threshold": 239.0418689715127,
    "width_percent_above_threshold": 1681267280684434.5,
    "height_percent_above_threshold": 10.902958954207726,
    "snr_percent_above_threshold": 2450.7560341313406,
    "area_percent_above_threshold": 3768.51551873697,
    "feature_explanation": "This peak's prominence is 239.0% above threshold, width is 1681267280684434.5% above threshold, height is 10.9% above threshold, S/N is 2450.8% above threshold, and area is 3768.5% above threshold.",
    "counterfactual_explanation": "If prominence were 239.0% lower, or width were 1681267280684434.5% lower, or height were 10.9% lower, or S/N were 2450.8% lower, or area were 3768.5% lower, this peak would fail detection.",
    "hybrid_explanation": "prominence: 172.634 (239.0% above threshold), width: 16.813 (1681267280684434.5% above threshold), height: 181.400 (10.9% above threshold), S/N: 19.090 (2450.8% above threshold), area: 6.946 (3768.5% above threshold).",
    "weakest_constraint_explanation": "The limiting factor is height, which is only 10.9% above its threshold.",
    "confidence": 0.301,
    "confidence_explanation": "Confidence is based on the weakest margin: 10.9% above threshold (lower means less robust)."
  },
  {
    "peak_id": "peak_5",
    "apex_time_table": 3.203555944493061,
    "apex_time_recomputed": 3.1256737092136517,
    "start_time": 3.1256737092136517,
    "end_time": 3.281438179772471,
    "table_confidence_percent": 4.6,
    "prominence": 8.668,
    "width_time": 0.15576447055881948,
    "width_samples": 30.0,
    "height": 8.668,
    "snr": 0.0,
    "peak_area": 0.0,
    "prominence_threshold": 50.91828774585579,
    "width_threshold_samples": 0,
    "height_threshold": 163.56611541897632,
    "snr_threshold": 0.7484238145508164,
    "area_threshold": 0.17955217405091117,
    "prominence_percent_above_threshold": -82.97664673395172,
    "width_percent_above_threshold": 2999999999999900.5,
    "height_percent_above_threshold": -94.7006138907213,
    "snr_percent_above_threshold": -100.0,
    "area_percent_above_threshold": -100.0,
    "feature_explanation": "This peak's prominence is 83.0% below threshold, width is 2999999999999900.5% above threshold, height is 94.7% below threshold, S/N is 100.0% below threshold, and area is 100.0% below threshold.",
    "counterfactual_explanation": "If prominence were 83.0% lower, or width were 2999999999999900.5% lower, or height were 94.7% lower, or S/N were 100.0% lower, or area were 100.0% lower, this peak would fail detection.",
    "hybrid_explanation": "prominence: 8.668 (-83.0% above threshold), width: 30.000 (2999999999999900.5% above threshold), height: 8.668 (-94.7% above threshold), S/N: 0.000 (-100.0% above threshold), area: 0.000 (-100.0% above threshold).",
    "weakest_constraint_explanation": "The limiting factor is S/N, which is only -100.0% above its threshold.",
    "confidence": 0.046,
    "confidence_explanation": "Confidence is based on the weakest margin: -100.0% above threshold (lower means less robust)."
  },
  {
    "peak_id": "peak_6",
    "apex_time_table": 4.408134516814601,
    "apex_time_recomputed": 4.408134516814601,
    "start_time": 4.190064258032254,
    "end_time": 4.626204775596949,
    "table_confidence_percent": 82.4,
    "prominence": 303.24329194059817,
    "width_time": 0.4361405175646951,
    "width_samples": 84.3197358423522,
    "height": 304.81786123691654,
    "snr": 4.7304024932506925,
    "peak_area": 60.600954747535425,
    "prominence_threshold": 50.91828774585579,
    "width_threshold_samples": 0,
    "height_threshold": 163.56611541897632,
    "snr_threshold": 0.7484238145508164,
    "area_threshold": 0.17955217405091117,
    "prominence_percent_above_threshold": 495.5488791260051,
    "width_percent_above_threshold": 8431973584235120.0,
    "height_percent_above_threshold": 86.35758418308241,
    "snr_percent_above_threshold": 532.0486335793245,
    "area_percent_above_threshold": 33651.16735169818,
    "feature_explanation": "This peak's prominence is 495.5% above threshold, width is 8431973584235120.0% above threshold, height is 86.4% above threshold, S/N is 532.0% above threshold, and area is 33651.2% above threshold.",
    "counterfactual_explanation": "If prominence were 495.5% lower, or width were 8431973584235120.0% lower, or height were 86.4% lower, or S/N were 532.0% lower, or area were 33651.2% lower, this peak would fail detection.",
    "hybrid_explanation": "prominence: 303.243 (495.5% above threshold), width: 84.320 (8431973584235120.0% above threshold), height: 304.818 (86.4% above threshold), S/N: 4.730 (532.0% above threshold), area: 60.601 (33651.2% above threshold).",
    "weakest_constraint_explanation": "The limiting factor is height, which is only 86.4% above its threshold.",
    "confidence": 0.8240000000000001,
    "confidence_explanation": "Confidence is based on the weakest margin: 86.4% above threshold (lower means less robust)."
  },
  {
    "peak_id": "peak_7",
    "apex_time_table": 5.88789698712339,
    "apex_time_recomputed": 5.88789698712339,
    "start_time": 5.81001475184398,
    "end_time": 5.9657792224028,
    "table_confidence_percent": 4.6,
    "prominence": 12.577,
    "width_time": 0.15576447055881992,
    "width_samples": 30.0,
    "height": 12.577,
    "snr": 0.005,
    "peak_area": 0.07,
    "prominence_threshold": 50.91828774585579,
    "width_threshold_samples": 0,
    "height_threshold": 163.56611541897632,
    "snr_threshold": 0.7484238145508164,
    "area_threshold": 0.17955217405091117,
    "prominence_percent_above_threshold": -75.2996407444521,
    "width_percent_above_threshold": 2999999999999900.5,
    "height_percent_above_threshold": -92.3107546035535,
    "snr_percent_above_threshold": -99.33192932897241,
    "area_percent_above_threshold": -61.014117278161265,
    "feature_explanation": "This peak's prominence is 75.3% below threshold, width is 2999999999999900.5% above threshold, height is 92.3% below threshold, S/N is 99.3% below threshold, and area is 61.0% below threshold.",
    "counterfactual_explanation": "If prominence were 75.3% lower, or width were 2999999999999900.5% lower, or height were 92.3% lower, or S/N were 99.3% lower, or area were 61.0% lower, this peak would fail detection.",
    "hybrid_explanation": "prominence: 12.577 (-75.3% above threshold), width: 30.000 (2999999999999900.5% above threshold), height: 12.577 (-92.3% above threshold), S/N: 0.005 (-99.3% above threshold), area: 0.070 (-61.0% above threshold).",
    "weakest_constraint_explanation": "The limiting factor is S/N, which is only -99.3% above its threshold.",
    "confidence": 0.046,
    "confidence_explanation": "Confidence is based on the weakest margin: -99.3% above threshold (lower means less robust)."
  },
  {
    "peak_id": "peak_8",
    "apex_time_table": 6.770562320290035,
    "apex_time_recomputed": 6.770562320290035,
    "start_time": 6.64595074384298,
    "end_time": 6.889981747718465,
    "table_confidence_percent": 73.4,
    "prominence": 325.4863535279791,
    "width_time": 0.2440310038754845,
    "width_samples": 47.36633998367097,
    "height": 325.36386526805563,
    "snr": 15.414921196358412,
    "peak_area": 36.138166172144,
    "prominence_threshold": 50.91828774585579,
    "width_threshold_samples": 0,
    "height_threshold": 163.56611541897632,
    "snr_threshold": 0.7484238145508164,
    "area_threshold": 0.17955217405091117,
    "prominence_percent_above_threshold": 539.2327156650515,
    "width_percent_above_threshold": 4736633998366997.0,
    "height_percent_above_threshold": 98.91886802754512,
    "snr_percent_above_threshold": 1959.651349497748,
    "area_percent_above_threshold": 20026.83297385037,
    "feature_explanation": "This peak's prominence is 539.2% above threshold, width is 4736633998366997.0% above threshold, height is 98.9% above threshold, S/N is 1959.7% above threshold, and area is 20026.8% above threshold.",
    "counterfactual_explanation": "If prominence were 539.2% lower, or width were 4736633998366997.0% lower, or height were 98.9% lower, or S/N were 1959.7% lower, or area were 20026.8% lower, this peak would fail detection.",
    "hybrid_explanation": "prominence: 325.486 (539.2% above threshold), width: 47.366 (4736633998366997.0% above threshold), height: 325.364 (98.9% above threshold), S/N: 15.415 (1959.7% above threshold), area: 36.138 (20026.8% above threshold).",
    "weakest_constraint_explanation": "The limiting factor is height, which is only 98.9% above its threshold.",
    "confidence": 0.7340000000000001,
    "confidence_explanation": "Confidence is based on the weakest margin: 98.9% above threshold (lower means less robust)."
  },
  {
    "peak_id": "peak_9",
    "apex_time_table": 8.053023127890986,
    "apex_time_recomputed": 8.053023127890986,
    "start_time": 7.995909488686085,
    "end_time": 8.110136767095886,
    "table_confidence_percent": 36.7,
    "prominence": 196.83269054753785,
    "width_time": 0.11422727840980151,
    "width_samples": 22.11228528258198,
    "height": 208.90061271782574,
    "snr": 18.2663712976932,
    "peak_area": 10.115833267584211,
    "prominence_threshold": 50.91828774585579,
    "width_threshold_samples": 0,
    "height_threshold": 163.56611541897632,
    "snr_threshold": 0.7484238145508164,
    "area_threshold": 0.17955217405091117,
    "prominence_percent_above_threshold": 286.56580820229556,
    "width_percent_above_threshold": 2211228528258098.0,
    "height_percent_above_threshold": 27.71631348138618,
    "snr_percent_above_threshold": 2340.645386017838,
    "area_percent_above_threshold": 5533.924134338754,
    "feature_explanation": "This peak's prominence is 286.6% above threshold, width is 2211228528258098.0% above threshold, height is 27.7% above threshold, S/N is 2340.6% above threshold, and area is 5533.9% above threshold.",
    "counterfactual_explanation": "If prominence were 286.6% lower, or width were 2211228528258098.0% lower, or height were 27.7% lower, or S/N were 2340.6% lower, or area were 5533.9% lower, this peak would fail detection.",
    "hybrid_explanation": "prominence: 196.833 (286.6% above threshold), width: 22.112 (2211228528258098.0% above threshold), height: 208.901 (27.7% above threshold), S/N: 18.266 (2340.6% above threshold), area: 10.116 (5533.9% above threshold).",
    "weakest_constraint_explanation": "The limiting factor is height, which is only 27.7% above its threshold.",
    "confidence": 0.36700000000000005,
    "confidence_explanation": "Confidence is based on the weakest margin: 27.7% above threshold (lower means less robust)."
  },
  {
    "peak_id": "peak_10",
    "apex_time_table": 8.577430178772346,
    "apex_time_recomputed": 8.546277284660581,
    "start_time": 8.499547943492937,
    "end_time": 8.655312414051755,
    "table_confidence_percent": 4.6,
    "prominence": 18.483,
    "width_time": 0.15576447055881815,
    "width_samples": 30.0,
    "height": 18.483,
    "snr": 0.148,
    "peak_area": 0.062,
    "prominence_threshold": 50.91828774585579,
    "width_threshold_samples": 0,
    "height_threshold": 163.56611541897632,
    "snr_threshold": 0.7484238145508164,
    "area_threshold": 0.17955217405091117,
    "prominence_percent_above_threshold": -63.700664695850215,
    "width_percent_above_threshold": 2999999999999900.5,
    "height_percent_above_threshold": -88.69998229605466,
    "snr_percent_above_threshold": -80.22510813758304,
    "area_percent_above_threshold": -65.46964673208568,
    "feature_explanation": "This peak's prominence is 63.7% below threshold, width is 2999999999999900.5% above threshold, height is 88.7% below threshold, S/N is 80.2% below threshold, and area is 65.5% below threshold.",
    "counterfactual_explanation": "If prominence were 63.7% lower, or width were 2999999999999900.5% lower, or height were 88.7% lower, or S/N were 80.2% lower, or area were 65.5% lower, this peak would fail detection.",
    "hybrid_explanation": "prominence: 18.483 (-63.7% above threshold), width: 30.000 (2999999999999900.5% above threshold), height: 18.483 (-88.7% above threshold), S/N: 0.148 (-80.2% above threshold), area: 0.062 (-65.5% above threshold).",
    "weakest_constraint_explanation": "The limiting factor is height, which is only -88.7% above its threshold.",
    "confidence": 0.046,
    "confidence_explanation": "Confidence is based on the weakest margin: -88.7% above threshold (lower means less robust)."
  },
  {
    "peak_id": "peak_11",
    "apex_time_table": 9.371828978622329,
    "apex_time_recomputed": 9.371828978622329,
    "start_time": 9.335483935491936,
    "end_time": 9.413366170771344,
    "table_confidence_percent": 39.1,
    "prominence": 277.2723029480718,
    "width_time": 0.0778822352794073,
    "width_samples": 14.884562862008579,
    "height": 296.9740870025339,
    "snr": 7.5691564571934595,
    "peak_area": 10.16033241718369,
    "prominence_threshold": 50.91828774585579,
    "width_threshold_samples": 0,
    "height_threshold": 163.56611541897632,
    "snr_threshold": 0.7484238145508164,
    "area_threshold": 0.17955217405091117,
    "prominence_percent_above_threshold": 444.54365066633414,
    "width_percent_above_threshold": 1488456286200758.0,
    "height_percent_above_threshold": 81.56210792304486,
    "snr_percent_above_threshold": 911.3462866940251,
    "area_percent_above_threshold": 5558.707543303138,
    "feature_explanation": "This peak's prominence is 444.5% above threshold, width is 1488456286200758.0% above threshold, height is 81.6% above threshold, S/N is 911.3% above threshold, and area is 5558.7% above threshold.",
    "counterfactual_explanation": "If prominence were 444.5% lower, or width were 1488456286200758.0% lower, or height were 81.6% lower, or S/N were 911.3% lower, or area were 5558.7% lower, this peak would fail detection.",
    "hybrid_explanation": "prominence: 277.272 (444.5% above threshold), width: 14.885 (1488456286200758.0% above threshold), height: 296.974 (81.6% above threshold), S/N: 7.569 (911.3% above threshold), area: 10.160 (5558.7% above threshold).",
    "weakest_constraint_explanation": "The limiting factor is height, which is only 81.6% above its threshold.",
    "confidence": 0.391,
    "confidence_explanation": "Confidence is based on the weakest margin: 81.6% above threshold (lower means less robust)."
  },
  {
    "peak_id": "peak_12",
    "apex_time_table": 9.875467433429176,
    "apex_time_recomputed": 9.875467433429176,
    "start_time": 9.745663707963494,
    "end_time": 10.000079009876234,
    "table_confidence_percent": 58.7,
    "prominence": 305.68348631993564,
    "width_time": 0.25441530191274,
    "width_samples": 49.38226116478836,
    "height": 309.93155812947816,
    "snr": 1.9038022145016367,
    "peak_area": 34.796774279612215,
    "prominence_threshold": 50.91828774585579,
    "width_threshold_samples": 0,
    "height_threshold": 163.56611541897632,
    "snr_threshold": 0.7484238145508164,
    "area_threshold": 0.17955217405091117,
    "prominence_percent_above_threshold": 500.341252332891,
    "width_percent_above_threshold": 4938226116478736.0,
    "height_percent_above_threshold": 89.48396331085154,
    "snr_percent_above_threshold": 154.37488458918787,
    "area_percent_above_threshold": 19279.756588046523,
    "feature_explanation": "This peak's prominence is 500.3% above threshold, width is 4938226116478736.0% above threshold, height is 89.5% above threshold, S/N is 154.4% above threshold, and area is 19279.8% above threshold.",
    "counterfactual_explanation": "If prominence were 500.3% lower, or width were 4938226116478736.0% lower, or height were 89.5% lower, or S/N were 154.4% lower, or area were 19279.8% lower, this peak would fail detection.",
    "hybrid_explanation": "prominence: 305.683 (500.3% above threshold), width: 49.382 (4938226116478736.0% above threshold), height: 309.932 (89.5% above threshold), S/N: 1.904 (154.4% above threshold), area: 34.797 (19279.8% above threshold).",
    "weakest_constraint_explanation": "The limiting factor is height, which is only 89.5% above its threshold.",
    "confidence": 0.5870000000000001,
    "confidence_explanation": "Confidence is based on the weakest margin: 89.5% above threshold (lower means less robust)."
  },
  {
    "peak_id": "peak_13",
    "apex_time_table": 10.61275259407426,
    "apex_time_recomputed": 10.586791848981122,
    "start_time": 10.534870358794848,
    "end_time": 10.690634829353668,
    "table_confidence_percent": 4.6,
    "prominence": 2.799,
    "width_time": 0.15576447055881992,
    "width_samples": 30.0,
    "height": 2.799,
    "snr": 0.532,
    "peak_area": 0.057,
    "prominence_threshold": 50.91828774585579,
    "width_threshold_samples": 0,
    "height_threshold": 163.56611541897632,
    "snr_threshold": 0.7484238145508164,
    "area_threshold": 0.17955217405091117,
    "prominence_percent_above_threshold": -94.50295733829383,
    "width_percent_above_threshold": 2999999999999900.5,
    "height_percent_above_threshold": -98.28876537611086,
    "snr_percent_above_threshold": -28.917280602663354,
    "area_percent_above_threshold": -68.25435264078847,
    "feature_explanation": "This peak's prominence is 94.5% below threshold, width is 2999999999999900.5% above threshold, height is 98.3% below threshold, S/N is 28.9% below threshold, and area is 68.3% below threshold.",
    "counterfactual_explanation": "If prominence were 94.5% lower, or width were 2999999999999900.5% lower, or height were 98.3% lower, or S/N were 28.9% lower, or area were 68.3% lower, this peak would fail detection.",
    "hybrid_explanation": "prominence: 2.799 (-94.5% above threshold), width: 30.000 (2999999999999900.5% above threshold), height: 2.799 (-98.3% above threshold), S/N: 0.532 (-28.9% above threshold), area: 0.057 (-68.3% above threshold).",
    "weakest_constraint_explanation": "The limiting factor is height, which is only -98.3% above its threshold.",
    "confidence": 0.046,
    "confidence_explanation": "Confidence is based on the weakest margin: -98.3% above threshold (lower means less robust)."
  },
  {
    "peak_id": "peak_14",
    "apex_time_table": 11.9315584448056,
    "apex_time_recomputed": 11.936750593824229,
    "start_time": 11.62002950368796,
    "end_time": 12.25866383297912,
    "table_confidence_percent": 94.4,
    "prominence": 276.2001087451974,
    "width_time": 0.6386343292911612,
    "width_samples": 122.47257252445706,
    "height": 276.78215395500354,
    "snr": 1.3222913641212315,
    "peak_area": 78.80541294394729,
    "prominence_threshold": 50.91828774585579,
    "width_threshold_samples": 0,
    "height_threshold": 163.56611541897632,
    "snr_threshold": 0.7484238145508164,
    "area_threshold": 0.17955217405091117,
    "prominence_percent_above_threshold": 442.43793531269546,
    "width_percent_above_threshold": 1.2247257252445608e+16,
    "height_percent_above_threshold": 69.21729372004901,
    "snr_percent_above_threshold": 76.67681578449435,
    "area_percent_above_threshold": 43789.97981255431,
    "feature_explanation": "This peak's prominence is 442.4% above threshold, width is 12247257252445608.0% above threshold, height is 69.2% above threshold, S/N is 76.7% above threshold, and area is 43790.0% above threshold.",
    "counterfactual_explanation": "If prominence were 442.4% lower, or width were 12247257252445608.0% lower, or height were 69.2% lower, or S/N were 76.7% lower, or area were 43790.0% lower, this peak would fail detection.",
    "hybrid_explanation": "prominence: 276.200 (442.4% above threshold), width: 122.473 (12247257252445608.0% above threshold), height: 276.782 (69.2% above threshold), S/N: 1.322 (76.7% above threshold), area: 78.805 (43790.0% above threshold).",
    "weakest_constraint_explanation": "The limiting factor is height, which is only 69.2% above its threshold.",
    "confidence": 0.9440000000000001,
    "confidence_explanation": "Confidence is based on the weakest margin: 69.2% above threshold (lower means less robust)."
  },
  {
    "peak_id": "peak_15",
    "apex_time_table": 13.421705213151643,
    "apex_time_recomputed": 13.421705213151643,
    "start_time": 13.29190148768596,
    "end_time": 13.551508938617326,
    "table_confidence_percent": 86.2,
    "prominence": 378.5214025278762,
    "width_time": 0.25960745093136595,
    "width_samples": 50.131859721074306,
    "height": 378.40344894371617,
    "snr": 15.35784549118617,
    "peak_area": 43.53861611569654,
    "prominence_threshold": 50.91828774585579,
    "width_threshold_samples": 0,
    "height_threshold": 163.56611541897632,
    "snr_threshold": 0.7484238145508164,
    "area_threshold": 0.17955217405091117,
    "prominence_percent_above_threshold": 643.3898885546948,
    "width_percent_above_threshold": 5013185972107330.0,
    "height_percent_above_threshold": 131.34586767829742,
    "snr_percent_above_threshold": 1952.025228566989,
    "area_percent_above_threshold": 24148.448310824337,
    "feature_explanation": "This peak's prominence is 643.4% above threshold, width is 5013185972107330.0% above threshold, height is 131.3% above threshold, S/N is 1952.0% above threshold, and area is 24148.4% above threshold.",
    "counterfactual_explanation": "If prominence were 643.4% lower, or width were 5013185972107330.0% lower, or height were 131.3% lower, or S/N were 1952.0% lower, or area were 24148.4% lower, this peak would fail detection.",
    "hybrid_explanation": "prominence: 378.521 (643.4% above threshold), width: 50.132 (5013185972107330.0% above threshold), height: 378.403 (131.3% above threshold), S/N: 15.358 (1952.0% above threshold), area: 43.539 (24148.4% above threshold).",
    "weakest_constraint_explanation": "The limiting factor is height, which is only 131.3% above its threshold.",
    "confidence": 0.862,
    "confidence_explanation": "Confidence is based on the weakest margin: 131.3% above threshold (lower means less robust)."
  },
  {
    "peak_id": "peak_16",
    "apex_time_table": 16.080085510688836,
    "apex_time_recomputed": 16.080085510688836,
    "start_time": 15.862015251906486,
    "end_time": 16.30854006750844,
    "table_confidence_percent": 70.5,
    "prominence": 260.6708659030745,
    "width_time": 0.44652481560195234,
    "width_samples": 85.43616472324766,
    "height": 267.41897972587986,
    "snr": 2.570645902093595,
    "peak_area": 51.958335105583046,
    "prominence_threshold": 50.91828774585579,
    "width_threshold_samples": 0,
    "height_threshold": 163.56611541897632,
    "snr_threshold": 0.7484238145508164,
    "area_threshold": 0.17955217405091117,
    "prominence_percent_above_threshold": 411.93957503861736,
    "width_percent_above_threshold": 8543616472324666.0,
    "height_percent_above_threshold": 63.492896460176574,
    "snr_percent_above_threshold": 243.4746265572036,
    "area_percent_above_threshold": 28837.736554975105,
    "feature_explanation": "This peak's prominence is 411.9% above threshold, width is 8543616472324666.0% above threshold, height is 63.5% above threshold, S/N is 243.5% above threshold, and area is 28837.7% above threshold.",
    "counterfactual_explanation": "If prominence were 411.9% lower, or width were 8543616472324666.0% lower, or height were 63.5% lower, or S/N were 243.5% lower, or area were 28837.7% lower, this peak would fail detection.",
    "hybrid_explanation": "prominence: 260.671 (411.9% above threshold), width: 85.436 (8543616472324666.0% above threshold), height: 267.419 (63.5% above threshold), S/N: 2.571 (243.5% above threshold), area: 51.958 (28837.7% above threshold).",
    "weakest_constraint_explanation": "The limiting factor is height, which is only 63.5% above its threshold.",
    "confidence": 0.705,
    "confidence_explanation": "Confidence is based on the weakest margin: 63.5% above threshold (lower means less robust)."
  },
  {
    "peak_id": "peak_17",
    "apex_time_table": 17.108131016377047,
    "apex_time_recomputed": 17.108131016377047,
    "start_time": 17.030248781097637,
    "end_time": 17.19639754969371,
    "table_confidence_percent": 31.0,
    "prominence": 182.98850566880378,
    "width_time": 0.16614876859607364,
    "width_samples": 31.71754486329428,
    "height": 196.82144403239687,
    "snr": 8.957406860280082,
    "peak_area": 14.079973017174014,
    "prominence_threshold": 50.91828774585579,
    "width_threshold_samples": 0,
    "height_threshold": 163.56611541897632,
    "snr_threshold": 0.7484238145508164,
    "area_threshold": 0.17955217405091117,
    "prominence_percent_above_threshold": 259.37678537451825,
    "width_percent_above_threshold": 3171754486329328.0,
    "height_percent_above_threshold": 20.33142899324635,
    "snr_percent_above_threshold": 1096.8361623629085,
    "area_percent_above_threshold": 7741.7168110600005,
    "feature_explanation": "This peak's prominence is 259.4% above threshold, width is 3171754486329328.0% above threshold, height is 20.3% above threshold, S/N is 1096.8% above threshold, and area is 7741.7% above threshold.",
    "counterfactual_explanation": "If prominence were 259.4% lower, or width were 3171754486329328.0% lower, or height were 20.3% lower, or S/N were 1096.8% lower, or area were 7741.7% lower, this peak would fail detection.",
    "hybrid_explanation": "prominence: 182.989 (259.4% above threshold), width: 31.718 (3171754486329328.0% above threshold), height: 196.821 (20.3% above threshold), S/N: 8.957 (1096.8% above threshold), area: 14.080 (7741.7% above threshold).",
    "weakest_constraint_explanation": "The limiting factor is height, which is only 20.3% above its threshold.",
    "confidence": 0.31,
    "confidence_explanation": "Confidence is based on the weakest margin: 20.3% above threshold (lower means less robust)."
  },
  {
    "peak_id": "peak_18",
    "apex_time_table": 18.5619327415927,
    "apex_time_recomputed": 18.5619327415927,
    "start_time": 18.354246780847603,
    "end_time": 18.780003000375046,
    "table_confidence_percent": 59.8,
    "prominence": 226.1654004120151,
    "width_time": 0.42575621952744314,
    "width_samples": 81.93547180720634,
    "height": 239.94026183059918,
    "snr": 1.3351523102892324,
    "peak_area": 43.995726231492384,
    "prominence_threshold": 50.91828774585579,
    "width_threshold_samples": 0,
    "height_threshold": 163.56611541897632,
    "snr_threshold": 0.7484238145508164,
    "area_threshold": 0.17955217405091117,
    "prominence_percent_above_threshold": 344.1732242467689,
    "width_percent_above_threshold": 8193547180720534.0,
    "height_percent_above_threshold": 46.69313458719104,
    "snr_percent_above_threshold": 78.3952199717956,
    "area_percent_above_threshold": 24403.031758901234,
    "feature_explanation": "This peak's prominence is 344.2% above threshold, width is 8193547180720534.0% above threshold, height is 46.7% above threshold, S/N is 78.4% above threshold, and area is 24403.0% above threshold.",
    "counterfactual_explanation": "If prominence were 344.2% lower, or width were 8193547180720534.0% lower, or height were 46.7% lower, or S/N were 78.4% lower, or area were 24403.0% lower, this peak would fail detection.",
    "hybrid_explanation": "prominence: 226.165 (344.2% above threshold), width: 81.935 (8193547180720534.0% above threshold), height: 239.940 (46.7% above threshold), S/N: 1.335 (78.4% above threshold), area: 43.996 (24403.0% above threshold).",
    "weakest_constraint_explanation": "The limiting factor is height, which is only 46.7% above its threshold.",
    "confidence": 0.598,
    "confidence_explanation": "Confidence is based on the weakest margin: 46.7% above threshold (lower means less robust)."
  },
  {
    "peak_id": "peak_19",
    "apex_time_table": 19.460174521815222,
    "apex_time_recomputed": 19.460174521815222,
    "start_time": 19.418637329666208,
    "end_time": 19.501711713964244,
    "table_confidence_percent": 55.8,
    "prominence": 326.6285170614766,
    "width_time": 0.08307438429803682,
    "width_samples": 15.886542635538262,
    "height": 326.7365823115301,
    "snr": 17.97727523665679,
    "peak_area": 12.294022666501416,
    "prominence_threshold": 50.91828774585579,
    "width_threshold_samples": 0,
    "height_threshold": 163.56611541897632,
    "snr_threshold": 0.7484238145508164,
    "area_threshold": 0.17955217405091117,
    "prominence_percent_above_threshold": 541.4758459509682,
    "width_percent_above_threshold": 1588654263553726.2,
    "height_percent_above_threshold": 99.75811094772958,
    "snr_percent_above_threshold": 2302.018066120232,
    "area_percent_above_threshold": 6747.047512226447,
    "feature_explanation": "This peak's prominence is 541.5% above threshold, width is 1588654263553726.2% above threshold, height is 99.8% above threshold, S/N is 2302.0% above threshold, and area is 6747.0% above threshold.",
    "counterfactual_explanation": "If prominence were 541.5% lower, or width were 1588654263553726.2% lower, or height were 99.8% lower, or S/N were 2302.0% lower, or area were 6747.0% lower, this peak would fail detection.",
    "hybrid_explanation": "prominence: 326.629 (541.5% above threshold), width: 15.887 (1588654263553726.2% above threshold), height: 326.737 (99.8% above threshold), S/N: 17.977 (2302.0% above threshold), area: 12.294 (6747.0% above threshold).",
    "weakest_constraint_explanation": "The limiting factor is height, which is only 99.8% above its threshold.",
    "confidence": 0.5579999999999999,
    "confidence_explanation": "Confidence is based on the weakest margin: 99.8% above threshold (lower means less robust)."
  },
  {
    "peak_id": "peak_20",
    "apex_time_table": 20.44668283535442,
    "apex_time_recomputed": 20.44668283535442,
    "start_time": 20.155922490311287,
    "end_time": 20.73225103137892,
    "table_confidence_percent": 84.8,
    "prominence": 258.1260030789374,
    "width_time": 0.5763285410676318,
    "width_samples": 111.1036691935501,
    "height": 269.1196425394429,
    "snr": 1.229265190279646,
    "peak_area": 69.37581930787654,
    "prominence_threshold": 50.91828774585579,
    "width_threshold_samples": 0,
    "height_threshold": 163.56611541897632,
    "snr_threshold": 0.7484238145508164,
    "area_threshold": 0.17955217405091117,
    "prominence_percent_above_threshold": 406.94164023601934,
    "width_percent_above_threshold": 1.111036691935491e+16,
    "height_percent_above_threshold": 64.53263675675743,
    "snr_percent_above_threshold": 64.24720410819872,
    "area_percent_above_threshold": 38538.25078954786,
    "feature_explanation": "This peak's prominence is 406.9% above threshold, width is 11110366919354910.0% above threshold, height is 64.5% above threshold, S/N is 64.2% above threshold, and area is 38538.3% above threshold.",
    "counterfactual_explanation": "If prominence were 406.9% lower, or width were 11110366919354910.0% lower, or height were 64.5% lower, or S/N were 64.2% lower, or area were 38538.3% lower, this peak would fail detection.",
    "hybrid_explanation": "prominence: 258.126 (406.9% above threshold), width: 111.104 (11110366919354910.0% above threshold), height: 269.120 (64.5% above threshold), S/N: 1.229 (64.2% above threshold), area: 69.376 (38538.3% above threshold).",
    "weakest_constraint_explanation": "The limiting factor is S/N, which is only 64.2% above its threshold.",
    "confidence": 0.848,
    "confidence_explanation": "Confidence is based on the weakest margin: 64.2% above threshold (lower means less robust)."
  },
  {
    "peak_id": "peak_21",
    "apex_time_table": 21.78106513314164,
    "apex_time_recomputed": 21.78106513314164,
    "start_time": 21.718759344918112,
    "end_time": 21.843370921365167,
    "table_confidence_percent": 72.3,
    "prominence": 388.8799713371747,
    "width_time": 0.12461157644705523,
    "width_samples": 24.121600805538947,
    "height": 388.72298770517244,
    "snr": 17.529392531141568,
    "peak_area": 21.683961666773612,
    "prominence_threshold": 50.91828774585579,
    "width_threshold_samples": 0,
    "height_threshold": 163.56611541897632,
    "snr_threshold": 0.7484238145508164,
    "area_threshold": 0.17955217405091117,
    "prominence_percent_above_threshold": 663.733402187754,
    "width_percent_above_threshold": 2412160080553795.0,
    "height_percent_above_threshold": 137.65496093702197,
    "snr_percent_above_threshold": 2242.1746061971894,
    "area_percent_above_threshold": 11976.691235509756,
    "feature_explanation": "This peak's prominence is 663.7% above threshold, width is 2412160080553795.0% above threshold, height is 137.7% above threshold, S/N is 2242.2% above threshold, and area is 11976.7% above threshold.",
    "counterfactual_explanation": "If prominence were 663.7% lower, or width were 2412160080553795.0% lower, or height were 137.7% lower, or S/N were 2242.2% lower, or area were 11976.7% lower, this peak would fail detection.",
    "hybrid_explanation": "prominence: 388.880 (663.7% above threshold), width: 24.122 (2412160080553795.0% above threshold), height: 388.723 (137.7% above threshold), S/N: 17.529 (2242.2% above threshold), area: 21.684 (11976.7% above threshold).",
    "weakest_constraint_explanation": "The limiting factor is height, which is only 137.7% above its threshold.",
    "confidence": 0.723,
    "confidence_explanation": "Confidence is based on the weakest margin: 137.7% above threshold (lower means less robust)."
  },
  {
    "peak_id": "peak_22",
    "apex_time_table": 22.803918489811224,
    "apex_time_recomputed": 22.803918489811224,
    "start_time": 22.492389548693584,
    "end_time": 23.089486685835727,
    "table_confidence_percent": 86.2,
    "prominence": 256.90219318553926,
    "width_time": 0.5970971371421427,
    "width_samples": 114.82621433117947,
    "height": 266.42375305560387,
    "snr": 1.2668102190478723,
    "peak_area": 70.75912299303175,
    "prominence_threshold": 50.91828774585579,
    "width_threshold_samples": 0,
    "height_threshold": 163.56611541897632,
    "snr_threshold": 0.7484238145508164,
    "area_threshold": 0.17955217405091117,
    "prominence_percent_above_threshold": 404.5381621389033,
    "width_percent_above_threshold": 1.1482621433117848e+16,
    "height_percent_above_threshold": 62.884441177291905,
    "snr_percent_above_threshold": 69.2637506207866,
    "area_percent_above_threshold": 39308.66957866427,
    "feature_explanation": "This peak's prominence is 404.5% above threshold, width is 11482621433117848.0% above threshold, height is 62.9% above threshold, S/N is 69.3% above threshold, and area is 39308.7% above threshold.",
    "counterfactual_explanation": "If prominence were 404.5% lower, or width were 11482621433117848.0% lower, or height were 62.9% lower, or S/N were 69.3% lower, or area were 39308.7% lower, this peak would fail detection.",
    "hybrid_explanation": "prominence: 256.902 (404.5% above threshold), width: 114.826 (11482621433117848.0% above threshold), height: 266.424 (62.9% above threshold), S/N: 1.267 (69.3% above threshold), area: 70.759 (39308.7% above threshold).",
    "weakest_constraint_explanation": "The limiting factor is height, which is only 62.9% above its threshold.",
    "confidence": 0.862,
    "confidence_explanation": "Confidence is based on the weakest margin: 62.9% above threshold (lower means less robust)."
  },
  {
    "peak_id": "peak_23",
    "apex_time_table": 24.008497062132765,
    "apex_time_recomputed": 23.94619127390924,
    "start_time": 23.930614826853358,
    "end_time": 24.086379297412176,
    "table_confidence_percent": 4.8,
    "prominence": 14.041,
    "width_time": 0.15576447055881815,
    "width_samples": 30.0,
    "height": 14.041,
    "snr": 0.894,
    "peak_area": 0.105,
    "prominence_threshold": 50.91828774585579,
    "width_threshold_samples": 0,
    "height_threshold": 163.56611541897632,
    "snr_threshold": 0.7484238145508164,
    "area_threshold": 0.17955217405091117,
    "prominence_percent_above_threshold": -72.42444586887589,
    "width_percent_above_threshold": 2999999999999900.5,
    "height_percent_above_threshold": -91.41570369631032,
    "snr_percent_above_threshold": 19.451035979734886,
    "area_percent_above_threshold": -41.52117591724189,
    "feature_explanation": "This peak's prominence is 72.4% below threshold, width is 2999999999999900.5% above threshold, height is 91.4% below threshold, S/N is 19.5% above threshold, and area is 41.5% below threshold.",
    "counterfactual_explanation": "If prominence were 72.4% lower, or width were 2999999999999900.5% lower, or height were 91.4% lower, or S/N were 19.5% lower, or area were 41.5% lower, this peak would fail detection.",
    "hybrid_explanation": "prominence: 14.041 (-72.4% above threshold), width: 30.000 (2999999999999900.5% above threshold), height: 14.041 (-91.4% above threshold), S/N: 0.894 (19.5% above threshold), area: 0.105 (-41.5% above threshold).",
    "weakest_constraint_explanation": "The limiting factor is height, which is only -91.4% above its threshold.",
    "confidence": 0.048,
    "confidence_explanation": "Confidence is based on the weakest margin: -91.4% above threshold (lower means less robust)."
  },
  {
    "peak_id": "peak_24",
    "apex_time_table": 24.673092136517063,
    "apex_time_recomputed": 24.673092136517063,
    "start_time": 24.631554944368045,
    "end_time": 24.719821477684707,
    "table_confidence_percent": 40.5,
    "prominence": 237.87760649510116,
    "width_time": 0.08826653331666279,
    "width_samples": 17.425032092532092,
    "height": 242.47207620577456,
    "snr": 17.70445562502852,
    "peak_area": 9.451741669687284,
    "prominence_threshold": 50.91828774585579,
    "width_threshold_samples": 0,
    "height_threshold": 163.56611541897632,
    "snr_threshold": 0.7484238145508164,
    "area_threshold": 0.17955217405091117,
    "prominence_percent_above_threshold": 367.1751879843247,
    "width_percent_above_threshold": 1742503209253109.5,
    "height_percent_above_threshold": 48.241018981639186,
    "snr_percent_above_threshold": 2265.5655099182345,
    "area_percent_above_threshold": 5164.0641750220675,
    "feature_explanation": "This peak's prominence is 367.2% above threshold, width is 1742503209253109.5% above threshold, height is 48.2% above threshold, S/N is 2265.6% above threshold, and area is 5164.1% above threshold.",
    "counterfactual_explanation": "If prominence were 367.2% lower, or width were 1742503209253109.5% lower, or height were 48.2% lower, or S/N were 2265.6% lower, or area were 5164.1% lower, this peak would fail detection.",
    "hybrid_explanation": "prominence: 237.878 (367.2% above threshold), width: 17.425 (1742503209253109.5% above threshold), height: 242.472 (48.2% above threshold), S/N: 17.704 (2265.6% above threshold), area: 9.452 (5164.1% above threshold).",
    "weakest_constraint_explanation": "The limiting factor is height, which is only 48.2% above its threshold.",
    "confidence": 0.405,
    "confidence_explanation": "Confidence is based on the weakest margin: 48.2% above threshold (lower means less robust)."
  },
  {
    "peak_id": "peak_25",
    "apex_time_table": 25.991897987248404,
    "apex_time_recomputed": 25.991897987248404,
    "start_time": 25.773827728466056,
    "end_time": 26.199583947993496,
    "table_confidence_percent": 81.3,
    "prominence": 284.4214935711753,
    "width_time": 0.4257562195274396,
    "width_samples": 81.33300546638839,
    "height": 286.84620837948813,
    "snr": 10.396140679700057,
    "peak_area": 55.608905523247756,
    "prominence_threshold": 50.91828774585579,
    "width_threshold_samples": 0,
    "height_threshold": 163.56611541897632,
    "snr_threshold": 0.7484238145508164,
    "area_threshold": 0.17955217405091117,
    "prominence_percent_above_threshold": 458.5841672264877,
    "width_percent_above_threshold": 8133300546638739.0,
    "height_percent_above_threshold": 75.37019060746692,
    "snr_percent_above_threshold": 1289.0713359969093,
    "area_percent_above_threshold": 30870.889557416394,
    "feature_explanation": "This peak's prominence is 458.6% above threshold, width is 8133300546638739.0% above threshold, height is 75.4% above threshold, S/N is 1289.1% above threshold, and area is 30870.9% above threshold.",
    "counterfactual_explanation": "If prominence were 458.6% lower, or width were 8133300546638739.0% lower, or height were 75.4% lower, or S/N were 1289.1% lower, or area were 30870.9% lower, this peak would fail detection.",
    "hybrid_explanation": "prominence: 284.421 (458.6% above threshold), width: 81.333 (8133300546638739.0% above threshold), height: 286.846 (75.4% above threshold), S/N: 10.396 (1289.1% above threshold), area: 55.609 (30870.9% above threshold).",
    "weakest_constraint_explanation": "The limiting factor is height, which is only 75.4% above its threshold.",
    "confidence": 0.813,
    "confidence_explanation": "Confidence is based on the weakest margin: 75.4% above threshold (lower means less robust)."
  },
  {
    "peak_id": "peak_26",
    "apex_time_table": 27.74684435554444,
    "apex_time_recomputed": 27.74684435554444,
    "start_time": 27.70530716339542,
    "end_time": 27.78838154769346,
    "table_confidence_percent": 41.4,
    "prominence": 253.25575778880824,
    "width_time": 0.08307438429804037,
    "width_samples": 15.694476562171076,
    "height": 261.2422691454764,
    "snr": 15.952919449704826,
    "peak_area": 9.570596807580094,
    "prominence_threshold": 50.91828774585579,
    "width_threshold_samples": 0,
    "height_threshold": 163.56611541897632,
    "snr_threshold": 0.7484238145508164,
    "area_threshold": 0.17955217405091117,
    "prominence_percent_above_threshold": 397.37681489382084,
    "width_percent_above_threshold": 1569447656217007.5,
    "height_percent_above_threshold": 59.716618858558576,
    "snr_percent_above_threshold": 2031.535520322711,
    "area_percent_above_threshold": 5230.2594959760245,
    "feature_explanation": "This peak's prominence is 397.4% above threshold, width is 1569447656217007.5% above threshold, height is 59.7% above threshold, S/N is 2031.5% above threshold, and area is 5230.3% above threshold.",
    "counterfactual_explanation": "If prominence were 397.4% lower, or width were 1569447656217007.5% lower, or height were 59.7% lower, or S/N were 2031.5% lower, or area were 5230.3% lower, this peak would fail detection.",
    "hybrid_explanation": "prominence: 253.256 (397.4% above threshold), width: 15.694 (1569447656217007.5% above threshold), height: 261.242 (59.7% above threshold), S/N: 15.953 (2031.5% above threshold), area: 9.571 (5230.3% above threshold).",
    "weakest_constraint_explanation": "The limiting factor is height, which is only 59.7% above its threshold.",
    "confidence": 0.414,
    "confidence_explanation": "Confidence is based on the weakest margin: 59.7% above threshold (lower means less robust)."
  },
  {
    "peak_id": "peak_27",
    "apex_time_table": 28.39067083385423,
    "apex_time_recomputed": 28.437400175021875,
    "start_time": 28.31278859857482,
    "end_time": 28.46855306913364,
    "table_confidence_percent": 4.6,
    "prominence": 19.389,
    "width_time": 0.1557644705588217,
    "width_samples": 30.0,
    "height": 19.389,
    "snr": 0.0,
    "peak_area": 0.031,
    "prominence_threshold": 50.91828774585579,
    "width_threshold_samples": 0,
    "height_threshold": 163.56611541897632,
    "snr_threshold": 0.7484238145508164,
    "area_threshold": 0.17955217405091117,
    "prominence_percent_above_threshold": -61.92134327694855,
    "width_percent_above_threshold": 2999999999999900.5,
    "height_percent_above_threshold": -88.14607784116234,
    "snr_percent_above_threshold": -100.0,
    "area_percent_above_threshold": -82.73482336604285,
    "feature_explanation": "This peak's prominence is 61.9% below threshold, width is 2999999999999900.5% above threshold, height is 88.1% below threshold, S/N is 100.0% below threshold, and area is 82.7% below threshold.",
    "counterfactual_explanation": "If prominence were 61.9% lower, or width were 2999999999999900.5% lower, or height were 88.1% lower, or S/N were 100.0% lower, or area were 82.7% lower, this peak would fail detection.",
    "hybrid_explanation": "prominence: 19.389 (-61.9% above threshold), width: 30.000 (2999999999999900.5% above threshold), height: 19.389 (-88.1% above threshold), S/N: 0.000 (-100.0% above threshold), area: 0.031 (-82.7% above threshold).",
    "weakest_constraint_explanation": "The limiting factor is S/N, which is only -100.0% above its threshold.",
    "confidence": 0.046,
    "confidence_explanation": "Confidence is based on the weakest margin: -100.0% above threshold (lower means less robust)."
  },
  {
    "peak_id": "peak_28",
    "apex_time_table": 28.868348543567944,
    "apex_time_recomputed": 28.868348543567944,
    "start_time": 28.83200350043755,
    "end_time": 28.904693586698336,
    "table_confidence_percent": 38.1,
    "prominence": 218.42276248135505,
    "width_time": 0.07269008626078488,
    "width_samples": 14.292046250142448,
    "height": 226.67321243284948,
    "snr": 20.257092057905272,
    "peak_area": 7.391214757501558,
    "prominence_threshold": 50.91828774585579,
    "width_threshold_samples": 0,
    "height_threshold": 163.56611541897632,
    "snr_threshold": 0.7484238145508164,
    "area_threshold": 0.17955217405091117,
    "prominence_percent_above_threshold": 328.9672181663892,
    "width_percent_above_threshold": 1429204625014145.0,
    "height_percent_above_threshold": 38.582011226606234,
    "snr_percent_above_threshold": 2606.6338168385287,
    "area_percent_above_threshold": 4016.4718815411356,
    "feature_explanation": "This peak's prominence is 329.0% above threshold, width is 1429204625014145.0% above threshold, height is 38.6% above threshold, S/N is 2606.6% above threshold, and area is 4016.5% above threshold.",
    "counterfactual_explanation": "If prominence were 329.0% lower, or width were 1429204625014145.0% lower, or height were 38.6% lower, or S/N were 2606.6% lower, or area were 4016.5% lower, this peak would fail detection.",
    "hybrid_explanation": "prominence: 218.423 (329.0% above threshold), width: 14.292 (1429204625014145.0% above threshold), height: 226.673 (38.6% above threshold), S/N: 20.257 (2606.6% above threshold), area: 7.391 (4016.5% above threshold).",
    "weakest_constraint_explanation": "The limiting factor is height, which is only 38.6% above its threshold.",
    "confidence": 0.381,
    "confidence_explanation": "Confidence is based on the weakest margin: 38.6% above threshold (lower means less robust)."
  },
  {
    "peak_id": "peak_29",
    "apex_time_table": 29.67313164145518,
    "apex_time_recomputed": 29.67313164145518,
    "start_time": 29.45506138267283,
    "end_time": 29.89120190023753,
    "table_confidence_percent": 82.0,
    "prominence": 310.0195335530889,
    "width_time": 0.4361405175646986,
    "width_samples": 83.77479296517777,
    "height": 314.5812151946148,
    "snr": 2.1625323599845903,
    "peak_area": 61.95589442016105,
    "prominence_threshold": 50.91828774585579,
    "width_threshold_samples": 0,
    "height_threshold": 163.56611541897632,
    "snr_threshold": 0.7484238145508164,
    "area_threshold": 0.17955217405091117,
    "prominence_percent_above_threshold": 508.85694959041746,
    "width_percent_above_threshold": 8377479296517678.0,
    "height_percent_above_threshold": 92.32664075246375,
    "snr_percent_above_threshold": 188.94488897076093,
    "area_percent_above_threshold": 34405.78905415746,
    "feature_explanation": "This peak's prominence is 508.9% above threshold, width is 8377479296517678.0% above threshold, height is 92.3% above threshold, S/N is 188.9% above threshold, and area is 34405.8% above threshold.",
    "counterfactual_explanation": "If prominence were 508.9% lower, or width were 8377479296517678.0% lower, or height were 92.3% lower, or S/N were 188.9% lower, or area were 34405.8% lower, this peak would fail detection.",
    "hybrid_explanation": "prominence: 310.020 (508.9% above threshold), width: 83.775 (8377479296517678.0% above threshold), height: 314.581 (92.3% above threshold), S/N: 2.163 (188.9% above threshold), area: 61.956 (34405.8% above threshold).",
    "weakest_constraint_explanation": "The limiting factor is height, which is only 92.3% above its threshold.",
    "confidence": 0.82,
    "confidence_explanation": "Confidence is based on the weakest margin: 92.3% above threshold (lower means less robust)."
  },
  {
    "peak_id": "peak_30",
    "apex_time_table": 30.94001600200025,
    "apex_time_recomputed": 30.94001600200025,
    "start_time": 30.70117714714339,
    "end_time": 31.163278409801222,
    "table_confidence_percent": 69.3,
    "prominence": 252.72953388861924,
    "width_time": 0.462101262657832,
    "width_samples": 89.02655203556151,
    "height": 262.77524184528306,
    "snr": 1.3505126056522392,
    "peak_area": 51.4483988636552,
    "prominence_threshold": 50.91828774585579,
    "width_threshold_samples": 0,
    "height_threshold": 163.56611541897632,
    "snr_threshold": 0.7484238145508164,
    "area_threshold": 0.17955217405091117,
    "prominence_percent_above_threshold": 396.3433475022709,
    "width_percent_above_threshold": 8902655203556052.0,
    "height_percent_above_threshold": 60.65383785155105,
    "snr_percent_above_threshold": 80.4475725378648,
    "area_percent_above_threshold": 28553.732061783474,
    "feature_explanation": "This peak's prominence is 396.3% above threshold, width is 8902655203556052.0% above threshold, height is 60.7% above threshold, S/N is 80.4% above threshold, and area is 28553.7% above threshold.",
    "counterfactual_explanation": "If prominence were 396.3% lower, or width were 8902655203556052.0% lower, or height were 60.7% lower, or S/N were 80.4% lower, or area were 28553.7% lower, this peak would fail detection.",
    "hybrid_explanation": "prominence: 252.730 (396.3% above threshold), width: 89.027 (8902655203556052.0% above threshold), height: 262.775 (60.7% above threshold), S/N: 1.351 (80.4% above threshold), area: 51.448 (28553.7% above threshold).",
    "weakest_constraint_explanation": "The limiting factor is height, which is only 60.7% above its threshold.",
    "confidence": 0.693,
    "confidence_explanation": "Confidence is based on the weakest margin: 60.7% above threshold (lower means less robust)."
  },
  {
    "peak_id": "peak_31",
    "apex_time_table": 32.09267308413551,
    "apex_time_recomputed": 32.09267308413551,
    "start_time": 32.03036729591199,
    "end_time": 32.154978872359045,
    "table_confidence_percent": 50.4,
    "prominence": 289.3140408561012,
    "width_time": 0.12461157644705878,
    "width_samples": 23.414336505159554,
    "height": 296.69418698634854,
    "snr": 13.378739548228953,
    "peak_area": 16.53068302945043,
    "prominence_threshold": 50.91828774585579,
    "width_threshold_samples": 0,
    "height_threshold": 163.56611541897632,
    "snr_threshold": 0.7484238145508164,
    "area_threshold": 0.17955217405091117,
    "prominence_percent_above_threshold": 468.1927921459776,
    "width_percent_above_threshold": 2341433650515855.5,
    "height_percent_above_threshold": 81.39098445076064,
    "snr_percent_above_threshold": 1687.5887014977613,
    "area_percent_above_threshold": 9106.618141400633,
    "feature_explanation": "This peak's prominence is 468.2% above threshold, width is 2341433650515855.5% above threshold, height is 81.4% above threshold, S/N is 1687.6% above threshold, and area is 9106.6% above threshold.",
    "counterfactual_explanation": "If prominence were 468.2% lower, or width were 2341433650515855.5% lower, or height were 81.4% lower, or S/N were 1687.6% lower, or area were 9106.6% lower, this peak would fail detection.",
    "hybrid_explanation": "prominence: 289.314 (468.2% above threshold), width: 23.414 (2341433650515855.5% above threshold), height: 296.694 (81.4% above threshold), S/N: 13.379 (1687.6% above threshold), area: 16.531 (9106.6% above threshold).",
    "weakest_constraint_explanation": "The limiting factor is height, which is only 81.4% above its threshold.",
    "confidence": 0.504,
    "confidence_explanation": "Confidence is based on the weakest margin: 81.4% above threshold (lower means less robust)."
  },
  {
    "peak_id": "peak_32",
    "apex_time_table": 32.78322890361295,
    "apex_time_recomputed": 32.78322890361295,
    "start_time": 32.72092311538942,
    "end_time": 32.8507268408551,
    "table_confidence_percent": 69.1,
    "prominence": 378.24844977224944,
    "width_time": 0.12980372546568475,
    "width_samples": 24.797647750819124,
    "height": 378.1251091957944,
    "snr": 15.620948842640273,
    "peak_area": 21.89282051382351,
    "prominence_threshold": 50.91828774585579,
    "width_threshold_samples": 0,
    "height_threshold": 163.56611541897632,
    "snr_threshold": 0.7484238145508164,
    "area_threshold": 0.17955217405091117,
    "prominence_percent_above_threshold": 642.8538281965988,
    "width_percent_above_threshold": 2479764775081812.5,
    "height_percent_above_threshold": 131.17569811279247,
    "snr_percent_above_threshold": 1987.1795550780998,
    "area_percent_above_threshold": 12093.013328602694,
    "feature_explanation": "This peak's prominence is 642.9% above threshold, width is 2479764775081812.5% above threshold, height is 131.2% above threshold, S/N is 1987.2% above threshold, and area is 12093.0% above threshold.",
    "counterfactual_explanation": "If prominence were 642.9% lower, or width were 2479764775081812.5% lower, or height were 131.2% lower, or S/N were 1987.2% lower, or area were 12093.0% lower, this peak would fail detection.",
    "hybrid_explanation": "prominence: 378.248 (642.9% above threshold), width: 24.798 (2479764775081812.5% above threshold), height: 378.125 (131.2% above threshold), S/N: 15.621 (1987.2% above threshold), area: 21.893 (12093.0% above threshold).",
    "weakest_constraint_explanation": "The limiting factor is height, which is only 131.2% above its threshold.",
    "confidence": 0.691,
    "confidence_explanation": "Confidence is based on the weakest margin: 131.2% above threshold (lower means less robust)."
  },
  {
    "peak_id": "peak_33",
    "apex_time_table": 34.53817527190898,
    "apex_time_recomputed": 34.543367420927616,
    "start_time": 34.2370306288286,
    "end_time": 34.82374346793349,
    "table_confidence_percent": 83.4,
    "prominence": 249.4740980800151,
    "width_time": 0.5867128391048908,
    "width_samples": 113.07484304617628,
    "height": 261.04082866281465,
    "snr": 1.269842526036632,
    "peak_area": 68.04602380162962,
    "prominence_threshold": 50.91828774585579,
    "width_threshold_samples": 0,
    "height_threshold": 163.56611541897632,
    "snr_threshold": 0.7484238145508164,
    "area_threshold": 0.17955217405091117,
    "prominence_percent_above_threshold": 389.9498964403406,
    "width_percent_above_threshold": 1.130748430461753e+16,
    "height_percent_above_threshold": 59.59346347142611,
    "snr_percent_above_threshold": 69.66890969373507,
    "area_percent_above_threshold": 37797.63290882543,
    "feature_explanation": "This peak's prominence is 389.9% above threshold, width is 11307484304617530.0% above threshold, height is 59.6% above threshold, S/N is 69.7% above threshold, and area is 37797.6% above threshold.",
    "counterfactual_explanation": "If prominence were 389.9% lower, or width were 11307484304617530.0% lower, or height were 59.6% lower, or S/N were 69.7% lower, or area were 37797.6% lower, this peak would fail detection.",
    "hybrid_explanation": "prominence: 249.474 (389.9% above threshold), width: 113.075 (11307484304617530.0% above threshold), height: 261.041 (59.6% above threshold), S/N: 1.270 (69.7% above threshold), area: 68.046 (37797.6% above threshold).",
    "weakest_constraint_explanation": "The limiting factor is height, which is only 59.6% above its threshold.",
    "confidence": 0.8340000000000001,
    "confidence_explanation": "Confidence is based on the weakest margin: 59.6% above threshold (lower means less robust)."
  },
  {
    "peak_id": "peak_34",
    "apex_time_table": 36.72407000875109,
    "apex_time_recomputed": 36.72407000875109,
    "start_time": 36.516384048006,
    "end_time": 36.93694811851481,
    "table_confidence_percent": 85.0,
    "prominence": 324.73080193003835,
    "width_time": 0.42056407050881006,
    "width_samples": 81.35819131297467,
    "height": 337.9716626381564,
    "snr": 1.809249043833427,
    "peak_area": 63.58427649109081,
    "prominence_threshold": 50.91828774585579,
    "width_threshold_samples": 0,
    "height_threshold": 163.56611541897632,
    "snr_threshold": 0.7484238145508164,
    "area_threshold": 0.17955217405091117,
    "prominence_percent_above_threshold": 537.7488645157122,
    "width_percent_above_threshold": 8135819131297367.0,
    "height_percent_above_threshold": 106.62694212211277,
    "snr_percent_above_threshold": 141.74124455396827,
    "area_percent_above_threshold": 35312.7020890662,
    "feature_explanation": "This peak's prominence is 537.7% above threshold, width is 8135819131297367.0% above threshold, height is 106.6% above threshold, S/N is 141.7% above threshold, and area is 35312.7% above threshold.",
    "counterfactual_explanation": "If prominence were 537.7% lower, or width were 8135819131297367.0% lower, or height were 106.6% lower, or S/N were 141.7% lower, or area were 35312.7% lower, this peak would fail detection.",
    "hybrid_explanation": "prominence: 324.731 (537.7% above threshold), width: 81.358 (8135819131297367.0% above threshold), height: 337.972 (106.6% above threshold), S/N: 1.809 (141.7% above threshold), area: 63.584 (35312.7% above threshold).",
    "weakest_constraint_explanation": "The limiting factor is height, which is only 106.6% above its threshold.",
    "confidence": 0.85,
    "confidence_explanation": "Confidence is based on the weakest margin: 106.6% above threshold (lower means less robust)."
  },
  {
    "peak_id": "peak_35",
    "apex_time_table": 37.86115064383048,
    "apex_time_recomputed": 37.86115064383048,
    "start_time": 37.79365270658832,
    "end_time": 37.92864858107263,
    "table_confidence_percent": 64.9,
    "prominence": 345.75361286124223,
    "width_time": 0.13499587448431072,
    "width_samples": 25.5555253633147,
    "height": 345.68774140097463,
    "snr": 17.39385791369956,
    "peak_area": 20.437360318773994,
    "prominence_threshold": 50.91828774585579,
    "width_threshold_samples": 0,
    "height_threshold": 163.56611541897632,
    "snr_threshold": 0.7484238145508164,
    "area_threshold": 0.17955217405091117,
    "prominence_percent_above_threshold": 579.0362130536939,
    "width_percent_above_threshold": 2555552536331370.5,
    "height_percent_above_threshold": 111.3443487457606,
    "snr_percent_above_threshold": 2224.0652656327993,
    "area_percent_above_threshold": 11282.407607595482,
    "feature_explanation": "This peak's prominence is 579.0% above threshold, width is 2555552536331370.5% above threshold, height is 111.3% above threshold, S/N is 2224.1% above threshold, and area is 11282.4% above threshold.",
    "counterfactual_explanation": "If prominence were 579.0% lower, or width were 2555552536331370.5% lower, or height were 111.3% lower, or S/N were 2224.1% lower, or area were 11282.4% lower, this peak would fail detection.",
    "hybrid_explanation": "prominence: 345.754 (579.0% above threshold), width: 25.556 (2555552536331370.5% above threshold), height: 345.688 (111.3% above threshold), S/N: 17.394 (2224.1% above threshold), area: 20.437 (11282.4% above threshold).",
    "weakest_constraint_explanation": "The limiting factor is height, which is only 111.3% above its threshold.",
    "confidence": 0.649,
    "confidence_explanation": "Confidence is based on the weakest margin: 111.3% above threshold (lower means less robust)."
  },
  {
    "peak_id": "peak_36",
    "apex_time_table": 38.49978497312164,
    "apex_time_recomputed": 38.49978497312164,
    "start_time": 38.45824778097262,
    "end_time": 38.53613001625203,
    "table_confidence_percent": 63.9,
    "prominence": 323.8822648923131,
    "width_time": 0.07788223527941085,
    "width_samples": 14.284193863809378,
    "height": 336.2478914027479,
    "snr": 27.11318624702999,
    "peak_area": 12.03713231549596,
    "prominence_threshold": 50.91828774585579,
    "width_threshold_samples": 0,
    "height_threshold": 163.56611541897632,
    "snr_threshold": 0.7484238145508164,
    "area_threshold": 0.17955217405091117,
    "prominence_percent_above_threshold": 536.082396385518,
    "width_percent_above_threshold": 1428419386380838.0,
    "height_percent_above_threshold": 105.57307394715916,
    "snr_percent_above_threshold": 3522.7049059499245,
    "area_percent_above_threshold": 6603.974696559723,
    "feature_explanation": "This peak's prominence is 536.1% above threshold, width is 1428419386380838.0% above threshold, height is 105.6% above threshold, S/N is 3522.7% above threshold, and area is 6604.0% above threshold.",
    "counterfactual_explanation": "If prominence were 536.1% lower, or width were 1428419386380838.0% lower, or height were 105.6% lower, or S/N were 3522.7% lower, or area were 6604.0% lower, this peak would fail detection.",
    "hybrid_explanation": "prominence: 323.882 (536.1% above threshold), width: 14.284 (1428419386380838.0% above threshold), height: 336.248 (105.6% above threshold), S/N: 27.113 (3522.7% above threshold), area: 12.037 (6604.0% above threshold).",
    "weakest_constraint_explanation": "The limiting factor is height, which is only 105.6% above its threshold.",
    "confidence": 0.639,
    "confidence_explanation": "Confidence is based on the weakest margin: 105.6% above threshold (lower means less robust)."
  },
  {
    "peak_id": "peak_37",
    "apex_time_table": 39.05534491811476,
    "apex_time_recomputed": 39.05534491811476,
    "start_time": 38.97746268283535,
    "end_time": 39.1384193024128,
    "table_confidence_percent": 31.0,
    "prominence": 165.740272277083,
    "width_time": 0.16095661957744767,
    "width_samples": 31.08511378548701,
    "height": 174.71379317610345,
    "snr": 13.749331630097682,
    "peak_area": 12.437869890116378,
    "prominence_threshold": 50.91828774585579,
    "width_threshold_samples": 0,
    "height_threshold": 163.56611541897632,
    "snr_threshold": 0.7484238145508164,
    "area_threshold": 0.17955217405091117,
    "prominence_percent_above_threshold": 225.50244639868606,
    "width_percent_above_threshold": 3108511378548601.0,
    "height_percent_above_threshold": 6.815395553395784,
    "snr_percent_above_threshold": 1737.1050416600729,
    "area_percent_above_threshold": 6827.161954936663,
    "feature_explanation": "This peak's prominence is 225.5% above threshold, width is 3108511378548601.0% above threshold, height is 6.8% above threshold, S/N is 1737.1% above threshold, and area is 6827.2% above threshold.",
    "counterfactual_explanation": "If prominence were 225.5% lower, or width were 3108511378548601.0% lower, or height were 6.8% lower, or S/N were 1737.1% lower, or area were 6827.2% lower, this peak would fail detection.",
    "hybrid_explanation": "prominence: 165.740 (225.5% above threshold), width: 31.085 (3108511378548601.0% above threshold), height: 174.714 (6.8% above threshold), S/N: 13.749 (1737.1% above threshold), area: 12.438 (6827.2% above threshold).",
    "weakest_constraint_explanation": "The limiting factor is height, which is only 6.8% above its threshold.",
    "confidence": 0.31,
    "confidence_explanation": "Confidence is based on the weakest margin: 6.8% above threshold (lower means less robust)."
  },
  {
    "peak_id": "peak_38",
    "apex_time_table": 40.19761770221277,
    "apex_time_recomputed": 40.19761770221277,
    "start_time": 40.11973546693336,
    "end_time": 40.265115639454926,
    "table_confidence_percent": 32.2,
    "prominence": 176.9923095947806,
    "width_time": 0.14538017252156266,
    "width_samples": 28.424838023373013,
    "height": 185.5482668850701,
    "snr": 14.342821962193083,
    "peak_area": 11.617774652730281,
    "prominence_threshold": 50.91828774585579,
    "width_threshold_samples": 0,
    "height_threshold": 163.56611541897632,
    "snr_threshold": 0.7484238145508164,
    "area_threshold": 0.17955217405091117,
    "prominence_percent_above_threshold": 247.60067046674385,
    "width_percent_above_threshold": 2842483802337201.5,
    "height_percent_above_threshold": 13.439306429565962,
    "snr_percent_above_threshold": 1816.4037385423462,
    "area_percent_above_threshold": 6370.41714428705,
    "feature_explanation": "This peak's prominence is 247.6% above threshold, width is 2842483802337201.5% above threshold, height is 13.4% above threshold, S/N is 1816.4% above threshold, and area is 6370.4% above threshold.",
    "counterfactual_explanation": "If prominence were 247.6% lower, or width were 2842483802337201.5% lower, or height were 13.4% lower, or S/N were 1816.4% lower, or area were 6370.4% lower, this peak would fail detection.",
    "hybrid_explanation": "prominence: 176.992 (247.6% above threshold), width: 28.425 (2842483802337201.5% above threshold), height: 185.548 (13.4% above threshold), S/N: 14.343 (1816.4% above threshold), area: 11.618 (6370.4% above threshold).",
    "weakest_constraint_explanation": "The limiting factor is height, which is only 13.4% above its threshold.",
    "confidence": 0.322,
    "confidence_explanation": "Confidence is based on the weakest margin: 13.4% above threshold (lower means less robust)."
  },
  {
    "peak_id": "peak_39",
    "apex_time_table": 40.96605575696962,
    "apex_time_recomputed": 40.96605575696962,
    "start_time": 40.9245185648206,
    "end_time": 41.00759294911864,
    "table_confidence_percent": 32.4,
    "prominence": 202.60013475077315,
    "width_time": 0.08307438429803682,
    "width_samples": 16.5052690880093,
    "height": 206.94291789123588,
    "snr": 16.2628741962923,
    "peak_area": 7.7486995016872715,
    "prominence_threshold": 50.91828774585579,
    "width_threshold_samples": 0,
    "height_threshold": 163.56611541897632,
    "snr_threshold": 0.7484238145508164,
    "area_threshold": 0.17955217405091117,
    "prominence_percent_above_threshold": 297.892670236663,
    "width_percent_above_threshold": 1650526908800830.0,
    "height_percent_above_threshold": 26.519430605262844,
    "snr_percent_above_threshold": 2072.949855430888,
    "area_percent_above_threshold": 4215.569857422146,
    "feature_explanation": "This peak's prominence is 297.9% above threshold, width is 1650526908800830.0% above threshold, height is 26.5% above threshold, S/N is 2072.9% above threshold, and area is 4215.6% above threshold.",
    "counterfactual_explanation": "If prominence were 297.9% lower, or width were 1650526908800830.0% lower, or height were 26.5% lower, or S/N were 2072.9% lower, or area were 4215.6% lower, this peak would fail detection.",
    "hybrid_explanation": "prominence: 202.600 (297.9% above threshold), width: 16.505 (1650526908800830.0% above threshold), height: 206.943 (26.5% above threshold), S/N: 16.263 (2072.9% above threshold), area: 7.749 (4215.6% above threshold).",
    "weakest_constraint_explanation": "The limiting factor is height, which is only 26.5% above its threshold.",
    "confidence": 0.324,
    "confidence_explanation": "Confidence is based on the weakest margin: 26.5% above threshold (lower means less robust)."
  }
]