[
  {
    "peak_id": "peak_1",
    "apex_time_table": 0.5740598824853107,
    "apex_time_recomputed": 0.6759957494686836,
    "start_time": 0.4721240155019377,
    "end_time": 0.6759957494686836,
    "table_confidence_percent": 4.9,
    "prominence": 19.044,
    "width_time": 0.20387173396674585,
    "width_samples": 38.0,
    "height": 19.044,
    "snr": 0.798,
    "peak_area": 0.168,
    "prominence_threshold": 103.13911448862717,
    "width_threshold_samples": 4,
    "height_threshold": 168.55920951891525,
    "snr_threshold": 0.4321257796970041,
    "area_threshold": 2.079154077708448,
    "prominence_percent_above_threshold": -81.53561808784006,
    "width_percent_above_threshold": 850.0,
    "height_percent_above_threshold": -88.70189291089257,
    "snr_percent_above_threshold": 84.66845476322608,
    "area_percent_above_threshold": -91.91979075523051,
    "feature_explanation": "This peak's prominence is 81.5% below threshold, width is 850.0% above threshold, height is 88.7% below threshold, S/N is 84.7% above threshold, and area is 91.9% below threshold.",
    "counterfactual_explanation": "If prominence were 81.5% lower, or width were 850.0% lower, or height were 88.7% lower, or S/N were 84.7% lower, or area were 91.9% lower, this peak would fail detection.",
    "hybrid_explanation": "prominence: 19.044 (-81.5% above threshold), width: 38.000 (850.0% above threshold), height: 19.044 (-88.7% above threshold), S/N: 0.798 (84.7% above threshold), area: 0.168 (-91.9% above threshold).",
    "weakest_constraint_explanation": "The limiting factor is area, which is only -91.9% above its threshold.",
    "confidence": 0.049,
    "confidence_explanation": "Confidence is based on the weakest margin: -91.9% above threshold (lower means less robust)."
  },
  {
    "peak_id": "peak_2",
    "apex_time_table": 1.5451331416427052,
    "apex_time_recomputed": 1.5451331416427052,
    "start_time": 1.2607857232154018,
    "end_time": 1.8348456057007123,
    "table_confidence_percent": 83.6,
    "prominence": 296.7441007916318,
    "width_time": 0.5740598824853105,
    "width_samples": 107.0,
    "height": 296.7069804241714,
    "snr": 3.7070978118608306,
    "peak_area": 69.63251993153132,
    "prominence_threshold": 103.13911448862717,
    "width_threshold_samples": 4,
    "height_threshold": 168.55920951891525,
    "snr_threshold": 0.4321257796970041,
    "area_threshold": 2.079154077708448,
    "prominence_percent_above_threshold": 187.71247674843366,
    "width_percent_above_threshold": 2575.0,
    "height_percent_above_threshold": 76.02537486441862,
    "snr_percent_above_threshold": 757.8747175093687,
    "area_percent_above_threshold": 3249.0793529009266,
    "feature_explanation": "This peak's prominence is 187.7% above threshold, width is 2575.0% above threshold, height is 76.0% above threshold, S/N is 757.9% above threshold, and area is 3249.1% above threshold.",
    "counterfactual_explanation": "If prominence were 187.7% lower, or width were 2575.0% lower, or height were 76.0% lower, or S/N were 757.9% lower, or area were 3249.1% lower, this peak would fail detection.",
    "hybrid_explanation": "prominence: 296.744 (187.7% above threshold), width: 107.000 (2575.0% above threshold), height: 296.707 (76.0% above threshold), S/N: 3.707 (757.9% above threshold), area: 69.633 (3249.1% above threshold).",
    "weakest_constraint_explanation": "The limiting factor is height, which is only 76.0% above its threshold.",
    "confidence": 0.836,
    "confidence_explanation": "Confidence is based on the weakest margin: 76.0% above threshold (lower means less robust)."
  },
  {
    "peak_id": "peak_3",
    "apex_time_table": 2.950775096887111,
    "apex_time_recomputed": 2.950775096887111,
    "start_time": 2.8488392299037377,
    "end_time": 3.058076009501188,
    "table_confidence_percent": 39.3,
    "prominence": 215.52898336738411,
    "width_time": 0.20923677959745035,
    "width_samples": 39.0,
    "height": 219.60247198709672,
    "snr": 3.8446019424520093,
    "peak_area": 20.060979554379415,
    "prominence_threshold": 103.13911448862717,
    "width_threshold_samples": 4,
    "height_threshold": 168.55920951891525,
    "snr_threshold": 0.4321257796970041,
    "area_threshold": 2.079154077708448,
    "prominence_percent_above_threshold": 108.96920090500663,
    "width_percent_above_threshold": 875.0,
    "height_percent_above_threshold": 30.2820964893369,
    "snr_percent_above_threshold": 789.695112647005,
    "area_percent_above_threshold": 864.8625741335024,
    "feature_explanation": "This peak's prominence is 109.0% above threshold, width is 875.0% above threshold, height is 30.3% above threshold, S/N is 789.7% above threshold, and area is 864.9% above threshold.",
    "counterfactual_explanation": "If prominence were 109.0% lower, or width were 875.0% lower, or height were 30.3% lower, or S/N were 789.7% lower, or area were 864.9% lower, this peak would fail detection.",
    "hybrid_explanation": "prominence: 215.529 (109.0% above threshold), width: 39.000 (875.0% above threshold), height: 219.602 (30.3% above threshold), S/N: 3.845 (789.7% above threshold), area: 20.061 (864.9% above threshold).",
    "weakest_constraint_explanation": "The limiting factor is height, which is only 30.3% above its threshold.",
    "confidence": 0.39299999999999996,
    "confidence_explanation": "Confidence is based on the weakest margin: 30.3% above threshold (lower means less robust)."
  },
  {
    "peak_id": "peak_4",
    "apex_time_table": 4.200830728841105,
    "apex_time_recomputed": 4.200830728841105,
    "start_time": 4.098894861857732,
    "end_time": 4.313496687085886,
    "table_confidence_percent": 37.1,
    "prominence": 201.51059052486542,
    "width_time": 0.2146018252281534,
    "width_samples": 40.0,
    "height": 202.51125131117735,
    "snr": 3.9842039368933095,
    "peak_area": 18.53423424511022,
    "prominence_threshold": 103.13911448862717,
    "width_threshold_samples": 4,
    "height_threshold": 168.55920951891525,
    "snr_threshold": 0.4321257796970041,
    "area_threshold": 2.079154077708448,
    "prominence_percent_above_threshold": 95.37746811573156,
    "width_percent_above_threshold": 900.0,
    "height_percent_above_threshold": 20.142501788638306,
    "snr_percent_above_threshold": 822.0009830672299,
    "area_percent_above_threshold": 791.4314934051368,
    "feature_explanation": "This peak's prominence is 95.4% above threshold, width is 900.0% above threshold, height is 20.1% above threshold, S/N is 822.0% above threshold, and area is 791.4% above threshold.",
    "counterfactual_explanation": "If prominence were 95.4% lower, or width were 900.0% lower, or height were 20.1% lower, or S/N were 822.0% lower, or area were 791.4% lower, this peak would fail detection.",
    "hybrid_explanation": "prominence: 201.511 (95.4% above threshold), width: 40.000 (900.0% above threshold), height: 202.511 (20.1% above threshold), S/N: 3.984 (822.0% above threshold), area: 18.534 (791.4% above threshold).",
    "weakest_constraint_explanation": "The limiting factor is height, which is only 20.1% above its threshold.",
    "confidence": 0.371,
    "confidence_explanation": "Confidence is based on the weakest margin: 20.1% above threshold (lower means less robust)."
  },
  {
    "peak_id": "peak_5",
    "apex_time_table": 5.456251406425803,
    "apex_time_recomputed": 5.456251406425803,
    "start_time": 5.38114076759595,
    "end_time": 5.536727090886361,
    "table_confidence_percent": 66.2,
    "prominence": 386.10349754224217,
    "width_time": 0.1555863232904109,
    "width_samples": 29.0,
    "height": 386.08927255519626,
    "snr": 3.886576152673198,
    "peak_area": 25.00034645601946,
    "prominence_threshold": 103.13911448862717,
    "width_threshold_samples": 4,
    "height_threshold": 168.55920951891525,
    "snr_threshold": 0.4321257796970041,
    "area_threshold": 2.079154077708448,
    "prominence_percent_above_threshold": 274.3521548120491,
    "width_percent_above_threshold": 625.0,
    "height_percent_above_threshold": 129.0526122287435,
    "snr_percent_above_threshold": 799.4085368844158,
    "area_percent_above_threshold": 1102.428753311719,
    "feature_explanation": "This peak's prominence is 274.4% above threshold, width is 625.0% above threshold, height is 129.1% above threshold, S/N is 799.4% above threshold, and area is 1102.4% above threshold.",
    "counterfactual_explanation": "If prominence were 274.4% lower, or width were 625.0% lower, or height were 129.1% lower, or S/N were 799.4% lower, or area were 1102.4% lower, this peak would fail detection.",
    "hybrid_explanation": "prominence: 386.103 (274.4% above threshold), width: 29.000 (625.0% above threshold), height: 386.089 (129.1% above threshold), S/N: 3.887 (799.4% above threshold), area: 25.000 (1102.4% above threshold).",
    "weakest_constraint_explanation": "The limiting factor is height, which is only 129.1% above its threshold.",
    "confidence": 0.662,
    "confidence_explanation": "Confidence is based on the weakest margin: 129.1% above threshold (lower means less robust)."
  },
  {
    "peak_id": "peak_6",
    "apex_time_table": 6.582910988873609,
    "apex_time_recomputed": 6.582910988873609,
    "start_time": 6.427324665583198,
    "end_time": 6.754592449056132,
    "table_confidence_percent": 66.1,
    "prominence": 305.8795583146623,
    "width_time": 0.3272677834729345,
    "width_samples": 61.0,
    "height": 306.7373809865234,
    "snr": 3.910595285479331,
    "peak_area": 41.143202092464506,
    "prominence_threshold": 103.13911448862717,
    "width_threshold_samples": 4,
    "height_threshold": 168.55920951891525,
    "snr_threshold": 0.4321257796970041,
    "area_threshold": 2.079154077708448,
    "prominence_percent_above_threshold": 196.56988993093466,
    "width_percent_above_threshold": 1425.0,
    "height_percent_above_threshold": 81.97604382577636,
    "snr_percent_above_threshold": 804.9669029747181,
    "area_percent_above_threshold": 1878.8433446842348,
    "feature_explanation": "This peak's prominence is 196.6% above threshold, width is 1425.0% above threshold, height is 82.0% above threshold, S/N is 805.0% above threshold, and area is 1878.8% above threshold.",
    "counterfactual_explanation": "If prominence were 196.6% lower, or width were 1425.0% lower, or height were 82.0% lower, or S/N were 805.0% lower, or area were 1878.8% lower, this peak would fail detection.",
    "hybrid_explanation": "prominence: 305.880 (196.6% above threshold), width: 61.000 (1425.0% above threshold), height: 306.737 (82.0% above threshold), S/N: 3.911 (805.0% above threshold), area: 41.143 (1878.8% above threshold).",
    "weakest_constraint_explanation": "The limiting factor is height, which is only 82.0% above its threshold.",
    "confidence": 0.6609999999999999,
    "confidence_explanation": "Confidence is based on the weakest margin: 82.0% above threshold (lower means less robust)."
  },
  {
    "peak_id": "peak_7",
    "apex_time_table": 7.532524065508189,
    "apex_time_recomputed": 7.532524065508189,
    "start_time": 7.446683335416927,
    "end_time": 7.634459932491561,
    "table_confidence_percent": 27.5,
    "prominence": 174.57142924852013,
    "width_time": 0.18777659707463368,
    "width_samples": 35.0,
    "height": 174.84055153068007,
    "snr": 3.4242241636262545,
    "peak_area": 14.928447665364372,
    "prominence_threshold": 103.13911448862717,
    "width_threshold_samples": 4,
    "height_threshold": 168.55920951891525,
    "snr_threshold": 0.4321257796970041,
    "area_threshold": 2.079154077708448,
    "prominence_percent_above_threshold": 69.25821994309402,
    "width_percent_above_threshold": 775.0,
    "height_percent_above_threshold": 3.7264899554835336,
    "snr_percent_above_threshold": 692.4137657390485,
    "area_percent_above_threshold": 618.0058383079453,
    "feature_explanation": "This peak's prominence is 69.3% above threshold, width is 775.0% above threshold, height is 3.7% above threshold, S/N is 692.4% above threshold, and area is 618.0% above threshold.",
    "counterfactual_explanation": "If prominence were 69.3% lower, or width were 775.0% lower, or height were 3.7% lower, or S/N were 692.4% lower, or area were 618.0% lower, this peak would fail detection.",
    "hybrid_explanation": "prominence: 174.571 (69.3% above threshold), width: 35.000 (775.0% above threshold), height: 174.841 (3.7% above threshold), S/N: 3.424 (692.4% above threshold), area: 14.928 (618.0% above threshold).",
    "weakest_constraint_explanation": "The limiting factor is height, which is only 3.7% above its threshold.",
    "confidence": 0.275,
    "confidence_explanation": "Confidence is based on the weakest margin: 3.7% above threshold (lower means less robust)."
  },
  {
    "peak_id": "peak_8",
    "apex_time_table": 8.272900362545318,
    "apex_time_recomputed": 8.176329541192649,
    "start_time": 8.170964495561945,
    "end_time": 8.374836229528691,
    "table_confidence_percent": 3.1,
    "prominence": 18.567,
    "width_time": 0.2038717339667464,
    "width_samples": 38.0,
    "height": 18.567,
    "snr": 0.01,
    "peak_area": 0.059,
    "prominence_threshold": 103.13911448862717,
    "width_threshold_samples": 4,
    "height_threshold": 168.55920951891525,
    "snr_threshold": 0.4321257796970041,
    "area_threshold": 2.079154077708448,
    "prominence_percent_above_threshold": -81.9981002434849,
    "width_percent_above_threshold": 850.0,
    "height_percent_above_threshold": -88.98487952512825,
    "snr_percent_above_threshold": -97.68585896286683,
    "area_percent_above_threshold": -97.1623074676107,
    "feature_explanation": "This peak's prominence is 82.0% below threshold, width is 850.0% above threshold, height is 89.0% below threshold, S/N is 97.7% below threshold, and area is 97.2% below threshold.",
    "counterfactual_explanation": "If prominence were 82.0% lower, or width were 850.0% lower, or height were 89.0% lower, or S/N were 97.7% lower, or area were 97.2% lower, this peak would fail detection.",
    "hybrid_explanation": "prominence: 18.567 (-82.0% above threshold), width: 38.000 (850.0% above threshold), height: 18.567 (-89.0% above threshold), S/N: 0.010 (-97.7% above threshold), area: 0.059 (-97.2% above threshold).",
    "weakest_constraint_explanation": "The limiting factor is S/N, which is only -97.7% above its threshold.",
    "confidence": 0.031,
    "confidence_explanation": "Confidence is based on the weakest margin: -97.7% above threshold (lower means less robust)."
  },
  {
    "peak_id": "peak_9",
    "apex_time_table": 8.900610701337667,
    "apex_time_recomputed": 8.900610701337667,
    "start_time": 8.852325290661332,
    "end_time": 8.954261157644705,
    "table_confidence_percent": 44.1,
    "prominence": 286.61686111855056,
    "width_time": 0.1019358669833732,
    "width_samples": 19.0,
    "height": 287.36673205231006,
    "snr": 3.9786898975054634,
    "peak_area": 12.691758399483845,
    "prominence_threshold": 103.13911448862717,
    "width_threshold_samples": 4,
    "height_threshold": 168.55920951891525,
    "snr_threshold": 0.4321257796970041,
    "area_threshold": 2.079154077708448,
    "prominence_percent_above_threshold": 177.89346703200067,
    "width_percent_above_threshold": 375.0,
    "height_percent_above_threshold": 70.48414789822715,
    "snr_percent_above_threshold": 820.7249565844515,
    "area_percent_above_threshold": 510.4289497136326,
    "feature_explanation": "This peak's prominence is 177.9% above threshold, width is 375.0% above threshold, height is 70.5% above threshold, S/N is 820.7% above threshold, and area is 510.4% above threshold.",
    "counterfactual_explanation": "If prominence were 177.9% lower, or width were 375.0% lower, or height were 70.5% lower, or S/N were 820.7% lower, or area were 510.4% lower, this peak would fail detection.",
    "hybrid_explanation": "prominence: 286.617 (177.9% above threshold), width: 19.000 (375.0% above threshold), height: 287.367 (70.5% above threshold), S/N: 3.979 (820.7% above threshold), area: 12.692 (510.4% above threshold).",
    "weakest_constraint_explanation": "The limiting factor is height, which is only 70.5% above its threshold.",
    "confidence": 0.441,
    "confidence_explanation": "Confidence is based on the weakest margin: 70.5% above threshold (lower means less robust)."
  },
  {
    "peak_id": "peak_10",
    "apex_time_table": 9.517590948868609,
    "apex_time_recomputed": 9.517590948868609,
    "start_time": 9.404924990623828,
    "end_time": 9.619526815851982,
    "table_confidence_percent": 38.7,
    "prominence": 213.74815528472422,
    "width_time": 0.2146018252281543,
    "width_samples": 40.0,
    "height": 222.20241255482148,
    "snr": 3.740636926438973,
    "peak_area": 19.117769469398525,
    "prominence_threshold": 103.13911448862717,
    "width_threshold_samples": 4,
    "height_threshold": 168.55920951891525,
    "snr_threshold": 0.4321257796970041,
    "area_threshold": 2.079154077708448,
    "prominence_percent_above_threshold": 107.24257362932232,
    "width_percent_above_threshold": 900.0,
    "height_percent_above_threshold": 31.82454592010087,
    "snr_percent_above_threshold": 765.6361416488077,
    "area_percent_above_threshold": 819.4974857500357,
    "feature_explanation": "This peak's prominence is 107.2% above threshold, width is 900.0% above threshold, height is 31.8% above threshold, S/N is 765.6% above threshold, and area is 819.5% above threshold.",
    "counterfactual_explanation": "If prominence were 107.2% lower, or width were 900.0% lower, or height were 31.8% lower, or S/N were 765.6% lower, or area were 819.5% lower, this peak would fail detection.",
    "hybrid_explanation": "prominence: 213.748 (107.2% above threshold), width: 40.000 (900.0% above threshold), height: 222.202 (31.8% above threshold), S/N: 3.741 (765.6% above threshold), area: 19.118 (819.5% above threshold).",
    "weakest_constraint_explanation": "The limiting factor is height, which is only 31.8% above its threshold.",
    "confidence": 0.387,
    "confidence_explanation": "Confidence is based on the weakest margin: 31.8% above threshold (lower means less robust)."
  },
  {
    "peak_id": "peak_11",
    "apex_time_table": 10.343807975997,
    "apex_time_recomputed": 10.343807975997,
    "start_time": 10.241872109013626,
    "end_time": 10.445743842980372,
    "table_confidence_percent": 4.1,
    "prominence": 19.977,
    "width_time": 0.2038717339667464,
    "width_samples": 38.0,
    "height": 19.977,
    "snr": 0.64,
    "peak_area": 0.388,
    "prominence_threshold": 103.13911448862717,
    "width_threshold_samples": 4,
    "height_threshold": 168.55920951891525,
    "snr_threshold": 0.4321257796970041,
    "area_threshold": 2.079154077708448,
    "prominence_percent_above_threshold": -80.63101462616997,
    "width_percent_above_threshold": 850.0,
    "height_percent_above_threshold": -88.1483782126077,
    "snr_percent_above_threshold": 48.10502637652217,
    "area_percent_above_threshold": -81.33856436327045,
    "feature_explanation": "This peak's prominence is 80.6% below threshold, width is 850.0% above threshold, height is 88.1% below threshold, S/N is 48.1% above threshold, and area is 81.3% below threshold.",
    "counterfactual_explanation": "If prominence were 80.6% lower, or width were 850.0% lower, or height were 88.1% lower, or S/N were 48.1% lower, or area were 81.3% lower, this peak would fail detection.",
    "hybrid_explanation": "prominence: 19.977 (-80.6% above threshold), width: 38.000 (850.0% above threshold), height: 19.977 (-88.1% above threshold), S/N: 0.640 (48.1% above threshold), area: 0.388 (-81.3% above threshold).",
    "weakest_constraint_explanation": "The limiting factor is height, which is only -88.1% above its threshold.",
    "confidence": 0.040999999999999995,
    "confidence_explanation": "Confidence is based on the weakest margin: -88.1% above threshold (lower means less robust)."
  },
  {
    "peak_id": "peak_12",
    "apex_time_table": 11.550943242905364,
    "apex_time_recomputed": 11.550943242905364,
    "start_time": 11.218310413801724,
    "end_time": 11.905036254531815,
    "table_confidence_percent": 89.1,
    "prominence": 270.6842856739621,
    "width_time": 0.6867258407300909,
    "width_samples": 128.0,
    "height": 271.6780692022528,
    "snr": 3.5245512670509536,
    "peak_area": 86.65943978193172,
    "prominence_threshold": 103.13911448862717,
    "width_threshold_samples": 4,
    "height_threshold": 168.55920951891525,
    "snr_threshold": 0.4321257796970041,
    "area_threshold": 2.079154077708448,
    "prominence_percent_above_threshold": 162.44581119009862,
    "width_percent_above_threshold": 3100.0,
    "height_percent_above_threshold": 61.176639340946736,
    "snr_percent_above_threshold": 715.6308724562283,
    "area_percent_above_threshold": 4068.0143242411327,
    "feature_explanation": "This peak's prominence is 162.4% above threshold, width is 3100.0% above threshold, height is 61.2% above threshold, S/N is 715.6% above threshold, and area is 4068.0% above threshold.",
    "counterfactual_explanation": "If prominence were 162.4% lower, or width were 3100.0% lower, or height were 61.2% lower, or S/N were 715.6% lower, or area were 4068.0% lower, this peak would fail detection.",
    "hybrid_explanation": "prominence: 270.684 (162.4% above threshold), width: 128.000 (3100.0% above threshold), height: 271.678 (61.2% above threshold), S/N: 3.525 (715.6% above threshold), area: 86.659 (4068.0% above threshold).",
    "weakest_constraint_explanation": "The limiting factor is height, which is only 61.2% above its threshold.",
    "confidence": 0.8909999999999999,
    "confidence_explanation": "Confidence is based on the weakest margin: 61.2% above threshold (lower means less robust)."
  },
  {
    "peak_id": "peak_13",
    "apex_time_table": 13.18191711463933,
    "apex_time_recomputed": 13.18191711463933,
    "start_time": 13.101441430178772,
    "end_time": 13.262392799099889,
    "table_confidence_percent": 70.1,
    "prominence": 403.1004140801603,
    "width_time": 0.1609513689211166,
    "width_samples": 30.0,
    "height": 402.9926169812602,
    "snr": 3.9363714558190654,
    "peak_area": 26.969151503331805,
    "prominence_threshold": 103.13911448862717,
    "width_threshold_samples": 4,
    "height_threshold": 168.55920951891525,
    "snr_threshold": 0.4321257796970041,
    "area_threshold": 2.079154077708448,
    "prominence_percent_above_threshold": 290.83175774658116,
    "width_percent_above_threshold": 650.0,
    "height_percent_above_threshold": 139.08074683753037,
    "snr_percent_above_threshold": 810.9318723310494,
    "area_percent_above_threshold": 1197.1213529810168,
    "feature_explanation": "This peak's prominence is 290.8% above threshold, width is 650.0% above threshold, height is 139.1% above threshold, S/N is 810.9% above threshold, and area is 1197.1% above threshold.",
    "counterfactual_explanation": "If prominence were 290.8% lower, or width were 650.0% lower, or height were 139.1% lower, or S/N were 810.9% lower, or area were 1197.1% lower, this peak would fail detection.",
    "hybrid_explanation": "prominence: 403.100 (290.8% above threshold), width: 30.000 (650.0% above threshold), height: 402.993 (139.1% above threshold), S/N: 3.936 (810.9% above threshold), area: 26.969 (1197.1% above threshold).",
    "weakest_constraint_explanation": "The limiting factor is height, which is only 139.1% above its threshold.",
    "confidence": 0.701,
    "confidence_explanation": "Confidence is based on the weakest margin: 139.1% above threshold (lower means less robust)."
  },
  {
    "peak_id": "peak_14",
    "apex_time_table": 14.42660770096262,
    "apex_time_recomputed": 14.42660770096262,
    "start_time": 14.28711651456432,
    "end_time": 14.582194024253033,
    "table_confidence_percent": 70.3,
    "prominence": 340.19573872612204,
    "width_time": 0.2950775096887135,
    "width_samples": 55.0,
    "height": 340.09954384404296,
    "snr": 3.6653472513187033,
    "peak_area": 44.97138990924019,
    "prominence_threshold": 103.13911448862717,
    "width_threshold_samples": 4,
    "height_threshold": 168.55920951891525,
    "snr_threshold": 0.4321257796970041,
    "area_threshold": 2.079154077708448,
    "prominence_percent_above_threshold": 229.84163225837503,
    "width_percent_above_threshold": 1275.0,
    "height_percent_above_threshold": 101.76859206608815,
    "snr_percent_above_threshold": 748.2130489619838,
    "area_percent_above_threshold": 2062.965717230811,
    "feature_explanation": "This peak's prominence is 229.8% above threshold, width is 1275.0% above threshold, height is 101.8% above threshold, S/N is 748.2% above threshold, and area is 2063.0% above threshold.",
    "counterfactual_explanation": "If prominence were 229.8% lower, or width were 1275.0% lower, or height were 101.8% lower, or S/N were 748.2% lower, or area were 2063.0% lower, this peak would fail detection.",
    "hybrid_explanation": "prominence: 340.196 (229.8% above threshold), width: 55.000 (1275.0% above threshold), height: 340.100 (101.8% above threshold), S/N: 3.665 (748.2% above threshold), area: 44.971 (2063.0% above threshold).",
    "weakest_constraint_explanation": "The limiting factor is height, which is only 101.8% above its threshold.",
    "confidence": 0.703,
    "confidence_explanation": "Confidence is based on the weakest margin: 101.8% above threshold (lower means less robust)."
  },
  {
    "peak_id": "peak_15",
    "apex_time_table": 16.10586698337292,
    "apex_time_recomputed": 16.10586698337292,
    "start_time": 15.76786910863858,
    "end_time": 16.459959994999373,
    "table_confidence_percent": 92.4,
    "prominence": 281.65839906943705,
    "width_time": 0.6920908863607931,
    "width_samples": 129.0,
    "height": 284.38316710639714,
    "snr": 3.7287393566811677,
    "peak_area": 86.93425652845818,
    "prominence_threshold": 103.13911448862717,
    "width_threshold_samples": 4,
    "height_threshold": 168.55920951891525,
    "snr_threshold": 0.4321257796970041,
    "area_threshold": 2.079154077708448,
    "prominence_percent_above_threshold": 173.0859194069333,
    "width_percent_above_threshold": 3125.0,
    "height_percent_above_threshold": 68.71410818670482,
    "snr_percent_above_threshold": 762.8828762069386,
    "area_percent_above_threshold": 4081.2320433833975,
    "feature_explanation": "This peak's prominence is 173.1% above threshold, width is 3125.0% above threshold, height is 68.7% above threshold, S/N is 762.9% above threshold, and area is 4081.2% above threshold.",
    "counterfactual_explanation": "If prominence were 173.1% lower, or width were 3125.0% lower, or height were 68.7% lower, or S/N were 762.9% lower, or area were 4081.2% lower, this peak would fail detection.",
    "hybrid_explanation": "prominence: 281.658 (173.1% above threshold), width: 129.000 (3125.0% above threshold), height: 284.383 (68.7% above threshold), S/N: 3.729 (762.9% above threshold), area: 86.934 (4081.2% above threshold).",
    "weakest_constraint_explanation": "The limiting factor is height, which is only 68.7% above its threshold.",
    "confidence": 0.924,
    "confidence_explanation": "Confidence is based on the weakest margin: 68.7% above threshold (lower means less robust)."
  },
  {
    "peak_id": "peak_16",
    "apex_time_table": 18.42893174146768,
    "apex_time_recomputed": 18.42893174146768,
    "start_time": 18.375281285160643,
    "end_time": 18.477217152144014,
    "table_confidence_percent": 36.0,
    "prominence": 229.88149810851377,
    "width_time": 0.10193586698337143,
    "width_samples": 19.0,
    "height": 230.54484299349252,
    "snr": 4.411354037772867,
    "peak_area": 9.45496851667001,
    "prominence_threshold": 103.13911448862717,
    "width_threshold_samples": 4,
    "height_threshold": 168.55920951891525,
    "snr_threshold": 0.4321257796970041,
    "area_threshold": 2.079154077708448,
    "prominence_percent_above_threshold": 122.8848863481973,
    "width_percent_above_threshold": 375.0,
    "height_percent_above_threshold": 36.77380408432766,
    "snr_percent_above_threshold": 920.8495408133251,
    "area_percent_above_threshold": 354.7507381988188,
    "feature_explanation": "This peak's prominence is 122.9% above threshold, width is 375.0% above threshold, height is 36.8% above threshold, S/N is 920.8% above threshold, and area is 354.8% above threshold.",
    "counterfactual_explanation": "If prominence were 122.9% lower, or width were 375.0% lower, or height were 36.8% lower, or S/N were 920.8% lower, or area were 354.8% lower, this peak would fail detection.",
    "hybrid_explanation": "prominence: 229.881 (122.9% above threshold), width: 19.000 (375.0% above threshold), height: 230.545 (36.8% above threshold), S/N: 4.411 (920.8% above threshold), area: 9.455 (354.8% above threshold).",
    "weakest_constraint_explanation": "The limiting factor is height, which is only 36.8% above its threshold.",
    "confidence": 0.36,
    "confidence_explanation": "Confidence is based on the weakest margin: 36.8% above threshold (lower means less robust)."
  },
  {
    "peak_id": "peak_17",
    "apex_time_table": 19.008356669583694,
    "apex_time_recomputed": 19.008356669583694,
    "start_time": 18.906420802600323,
    "end_time": 19.11029253656707,
    "table_confidence_percent": 3.1,
    "prominence": 27.762,
    "width_time": 0.2038717339667464,
    "width_samples": 38.0,
    "height": 27.762,
    "snr": 0.036,
    "peak_area": 1.036,
    "prominence_threshold": 103.13911448862717,
    "width_threshold_samples": 4,
    "height_threshold": 168.55920951891525,
    "snr_threshold": 0.4321257796970041,
    "area_threshold": 2.079154077708448,
    "prominence_percent_above_threshold": -73.08295680290989,
    "width_percent_above_threshold": 850.0,
    "height_percent_above_threshold": -83.52982309347824,
    "snr_percent_above_threshold": -91.66909226632063,
    "area_percent_above_threshold": -50.172042990588096,
    "feature_explanation": "This peak's prominence is 73.1% below threshold, width is 850.0% above threshold, height is 83.5% below threshold, S/N is 91.7% below threshold, and area is 50.2% below threshold.",
    "counterfactual_explanation": "If prominence were 73.1% lower, or width were 850.0% lower, or height were 83.5% lower, or S/N were 91.7% lower, or area were 50.2% lower, this peak would fail detection.",
    "hybrid_explanation": "prominence: 27.762 (-73.1% above threshold), width: 38.000 (850.0% above threshold), height: 27.762 (-83.5% above threshold), S/N: 0.036 (-91.7% above threshold), area: 1.036 (-50.2% above threshold).",
    "weakest_constraint_explanation": "The limiting factor is S/N, which is only -91.7% above its threshold.",
    "confidence": 0.031,
    "confidence_explanation": "Confidence is based on the weakest margin: -91.7% above threshold (lower means less robust)."
  },
  {
    "peak_id": "peak_18",
    "apex_time_table": 19.845303787973496,
    "apex_time_recomputed": 19.845303787973496,
    "start_time": 19.689717464683085,
    "end_time": 19.984794974371795,
    "table_confidence_percent": 77.4,
    "prominence": 369.13778801026507,
    "width_time": 0.29507750968870994,
    "width_samples": 55.0,
    "height": 369.02713648192844,
    "snr": 3.96977272898562,
    "peak_area": 47.65421946636109,
    "prominence_threshold": 103.13911448862717,
    "width_threshold_samples": 4,
    "height_threshold": 168.55920951891525,
    "snr_threshold": 0.4321257796970041,
    "area_threshold": 2.079154077708448,
    "prominence_percent_above_threshold": 257.9028090753763,
    "width_percent_above_threshold": 1275.0,
    "height_percent_above_threshold": 118.9302723566209,
    "snr_percent_above_threshold": 818.6613980237714,
    "area_percent_above_threshold": 2192.000385025985,
    "feature_explanation": "This peak's prominence is 257.9% above threshold, width is 1275.0% above threshold, height is 118.9% above threshold, S/N is 818.7% above threshold, and area is 2192.0% above threshold.",
    "counterfactual_explanation": "If prominence were 257.9% lower, or width were 1275.0% lower, or height were 118.9% lower, or S/N were 818.7% lower, or area were 2192.0% lower, this peak would fail detection.",
    "hybrid_explanation": "prominence: 369.138 (257.9% above threshold), width: 55.000 (1275.0% above threshold), height: 369.027 (118.9% above threshold), S/N: 3.970 (818.7% above threshold), area: 47.654 (2192.0% above threshold).",
    "weakest_constraint_explanation": "The limiting factor is height, which is only 118.9% above its threshold.",
    "confidence": 0.774,
    "confidence_explanation": "Confidence is based on the weakest margin: 118.9% above threshold (lower means less robust)."
  },
  {
    "peak_id": "peak_19",
    "apex_time_table": 20.43545880735092,
    "apex_time_recomputed": 20.43545880735092,
    "start_time": 20.387173396674584,
    "end_time": 20.489109263657955,
    "table_confidence_percent": 51.0,
    "prominence": 308.05097568187733,
    "width_time": 0.10193586698337143,
    "width_samples": 19.0,
    "height": 319.00323620506765,
    "snr": 4.412115880093876,
    "peak_area": 13.656134000070542,
    "prominence_threshold": 103.13911448862717,
    "width_threshold_samples": 4,
    "height_threshold": 168.55920951891525,
    "snr_threshold": 0.4321257796970041,
    "area_threshold": 2.079154077708448,
    "prominence_percent_above_threshold": 198.6752186202308,
    "width_percent_above_threshold": 375.0,
    "height_percent_above_threshold": 89.25292608783263,
    "snr_percent_above_threshold": 921.0258418712123,
    "area_percent_above_threshold": 556.8120249713159,
    "feature_explanation": "This peak's prominence is 198.7% above threshold, width is 375.0% above threshold, height is 89.3% above threshold, S/N is 921.0% above threshold, and area is 556.8% above threshold.",
    "counterfactual_explanation": "If prominence were 198.7% lower, or width were 375.0% lower, or height were 89.3% lower, or S/N were 921.0% lower, or area were 556.8% lower, this peak would fail detection.",
    "hybrid_explanation": "prominence: 308.051 (198.7% above threshold), width: 19.000 (375.0% above threshold), height: 319.003 (89.3% above threshold), S/N: 4.412 (921.0% above threshold), area: 13.656 (556.8% above threshold).",
    "weakest_constraint_explanation": "The limiting factor is height, which is only 89.3% above its threshold.",
    "confidence": 0.51,
    "confidence_explanation": "Confidence is based on the weakest margin: 89.3% above threshold (lower means less robust)."
  },
  {
    "peak_id": "peak_20",
    "apex_time_table": 21.37434179272409,
    "apex_time_recomputed": 21.37434179272409,
    "start_time": 21.31532629078635,
    "end_time": 21.433357294661832,
    "table_confidence_percent": 43.4,
    "prominence": 255.59754758124396,
    "width_time": 0.11803100387548326,
    "width_samples": 22.0,
    "height": 262.65923662159975,
    "snr": 4.656369153094009,
    "peak_area": 11.768417596624749,
    "prominence_threshold": 103.13911448862717,
    "width_threshold_samples": 4,
    "height_threshold": 168.55920951891525,
    "snr_threshold": 0.4321257796970041,
    "area_threshold": 2.079154077708448,
    "prominence_percent_above_threshold": 147.8182490207708,
    "width_percent_above_threshold": 450.0,
    "height_percent_above_threshold": 55.826096581287565,
    "snr_percent_above_threshold": 977.549494121582,
    "area_percent_above_threshold": 466.01950393187695,
    "feature_explanation": "This peak's prominence is 147.8% above threshold, width is 450.0% above threshold, height is 55.8% above threshold, S/N is 977.5% above threshold, and area is 466.0% above threshold.",
    "counterfactual_explanation": "If prominence were 147.8% lower, or width were 450.0% lower, or height were 55.8% lower, or S/N were 977.5% lower, or area were 466.0% lower, this peak would fail detection.",
    "hybrid_explanation": "prominence: 255.598 (147.8% above threshold), width: 22.000 (450.0% above threshold), height: 262.659 (55.8% above threshold), S/N: 4.656 (977.5% above threshold), area: 11.768 (466.0% above threshold).",
    "weakest_constraint_explanation": "The limiting factor is height, which is only 55.8% above its threshold.",
    "confidence": 0.434,
    "confidence_explanation": "Confidence is based on the weakest margin: 55.8% above threshold (lower means less robust)."
  },
  {
    "peak_id": "peak_21",
    "apex_time_table": 22.420525690711337,
    "apex_time_recomputed": 22.420525690711337,
    "start_time": 22.3668752344043,
    "end_time": 22.47954119264908,
    "table_confidence_percent": 30.9,
    "prominence": 209.44035099385036,
    "width_time": 0.11266595824477932,
    "width_samples": 21.0,
    "height": 214.95153753463154,
    "snr": 3.8713749428408004,
    "peak_area": 9.617309379934055,
    "prominence_threshold": 103.13911448862717,
    "width_threshold_samples": 4,
    "height_threshold": 168.55920951891525,
    "snr_threshold": 0.4321257796970041,
    "area_threshold": 2.079154077708448,
    "prominence_percent_above_threshold": 103.06588051708034,
    "width_percent_above_threshold": 425.0,
    "height_percent_above_threshold": 27.522867571653077,
    "snr_percent_above_threshold": 795.8907625356934,
    "area_percent_above_threshold": 362.5587628663783,
    "feature_explanation": "This peak's prominence is 103.1% above threshold, width is 425.0% above threshold, height is 27.5% above threshold, S/N is 795.9% above threshold, and area is 362.6% above threshold.",
    "counterfactual_explanation": "If prominence were 103.1% lower, or width were 425.0% lower, or height were 27.5% lower, or S/N were 795.9% lower, or area were 362.6% lower, this peak would fail detection.",
    "hybrid_explanation": "prominence: 209.440 (103.1% above threshold), width: 21.000 (425.0% above threshold), height: 214.952 (27.5% above threshold), S/N: 3.871 (795.9% above threshold), area: 9.617 (362.6% above threshold).",
    "weakest_constraint_explanation": "The limiting factor is height, which is only 27.5% above its threshold.",
    "confidence": 0.309,
    "confidence_explanation": "Confidence is based on the weakest margin: 27.5% above threshold (lower means less robust)."
  },
  {
    "peak_id": "peak_22",
    "apex_time_table": 22.86582447805976,
    "apex_time_recomputed": 22.86582447805976,
    "start_time": 22.7853487935992,
    "end_time": 22.951665208151017,
    "table_confidence_percent": 52.8,
    "prominence": 304.06330750900776,
    "width_time": 0.16631641455181523,
    "width_samples": 31.0,
    "height": 303.92009710375754,
    "snr": 4.062140228745102,
    "peak_area": 21.008062987029465,
    "prominence_threshold": 103.13911448862717,
    "width_threshold_samples": 4,
    "height_threshold": 168.55920951891525,
    "snr_threshold": 0.4321257796970041,
    "area_threshold": 2.079154077708448,
    "prominence_percent_above_threshold": 194.8089180487737,
    "width_percent_above_threshold": 675.0,
    "height_percent_above_threshold": 80.3046525735234,
    "snr_percent_above_threshold": 840.0365401928518,
    "area_percent_above_threshold": 910.4139569196153,
    "feature_explanation": "This peak's prominence is 194.8% above threshold, width is 675.0% above threshold, height is 80.3% above threshold, S/N is 840.0% above threshold, and area is 910.4% above threshold.",
    "counterfactual_explanation": "If prominence were 194.8% lower, or width were 675.0% lower, or height were 80.3% lower, or S/N were 840.0% lower, or area were 910.4% lower, this peak would fail detection.",
    "hybrid_explanation": "prominence: 304.063 (194.8% above threshold), width: 31.000 (675.0% above threshold), height: 303.920 (80.3% above threshold), S/N: 4.062 (840.0% above threshold), area: 21.008 (910.4% above threshold).",
    "weakest_constraint_explanation": "The limiting factor is height, which is only 80.3% above its threshold.",
    "confidence": 0.528,
    "confidence_explanation": "Confidence is based on the weakest margin: 80.3% above threshold (lower means less robust)."
  },
  {
    "peak_id": "peak_23",
    "apex_time_table": 23.783247280910118,
    "apex_time_recomputed": 23.783247280910118,
    "start_time": 23.552550318789848,
    "end_time": 24.040769471183896,
    "table_confidence_percent": 67.4,
    "prominence": 259.50506069142324,
    "width_time": 0.48821915239404845,
    "width_samples": 91.0,
    "height": 264.8602081225793,
    "snr": 3.119704785955954,
    "peak_area": 57.44251191419773,
    "prominence_threshold": 103.13911448862717,
    "width_threshold_samples": 4,
    "height_threshold": 168.55920951891525,
    "snr_threshold": 0.4321257796970041,
    "area_threshold": 2.079154077708448,
    "prominence_percent_above_threshold": 151.6068341075762,
    "width_percent_above_threshold": 2175.0,
    "height_percent_above_threshold": 57.13185229007461,
    "snr_percent_above_threshold": 621.9436868921391,
    "area_percent_above_threshold": 2662.7828322135865,
    "feature_explanation": "This peak's prominence is 151.6% above threshold, width is 2175.0% above threshold, height is 57.1% above threshold, S/N is 621.9% above threshold, and area is 2662.8% above threshold.",
    "counterfactual_explanation": "If prominence were 151.6% lower, or width were 2175.0% lower, or height were 57.1% lower, or S/N were 621.9% lower, or area were 2662.8% lower, this peak would fail detection.",
    "hybrid_explanation": "prominence: 259.505 (151.6% above threshold), width: 91.000 (2175.0% above threshold), height: 264.860 (57.1% above threshold), S/N: 3.120 (621.9% above threshold), area: 57.443 (2662.8% above threshold).",
    "weakest_constraint_explanation": "The limiting factor is height, which is only 57.1% above its threshold.",
    "confidence": 0.674,
    "confidence_explanation": "Confidence is based on the weakest margin: 57.1% above threshold (lower means less robust)."
  },
  {
    "peak_id": "peak_24",
    "apex_time_table": 25.269364920615075,
    "apex_time_recomputed": 25.269364920615075,
    "start_time": 25.011842730341293,
    "end_time": 25.516157019627453,
    "table_confidence_percent": 68.6,
    "prominence": 253.95698974774544,
    "width_time": 0.5043142892861603,
    "width_samples": 94.0,
    "height": 254.3895990637078,
    "snr": 3.498221047709969,
    "peak_area": 57.41612401792406,
    "prominence_threshold": 103.13911448862717,
    "width_threshold_samples": 4,
    "height_threshold": 168.55920951891525,
    "snr_threshold": 0.4321257796970041,
    "area_threshold": 2.079154077708448,
    "prominence_percent_above_threshold": 146.22762276648058,
    "width_percent_above_threshold": 2250.0,
    "height_percent_above_threshold": 50.920023764801115,
    "snr_percent_above_threshold": 709.5376883468593,
    "area_percent_above_threshold": 2661.5136671932264,
    "feature_explanation": "This peak's prominence is 146.2% above threshold, width is 2250.0% above threshold, height is 50.9% above threshold, S/N is 709.5% above threshold, and area is 2661.5% above threshold.",
    "counterfactual_explanation": "If prominence were 146.2% lower, or width were 2250.0% lower, or height were 50.9% lower, or S/N were 709.5% lower, or area were 2661.5% lower, this peak would fail detection.",
    "hybrid_explanation": "prominence: 253.957 (146.2% above threshold), width: 94.000 (2250.0% above threshold), height: 254.390 (50.9% above threshold), S/N: 3.498 (709.5% above threshold), area: 57.416 (2661.5% above threshold).",
    "weakest_constraint_explanation": "The limiting factor is height, which is only 50.9% above its threshold.",
    "confidence": 0.6859999999999999,
    "confidence_explanation": "Confidence is based on the weakest margin: 50.9% above threshold (lower means less robust)."
  },
  {
    "peak_id": "peak_25",
    "apex_time_table": 27.30271721465183,
    "apex_time_recomputed": 27.30271721465183,
    "start_time": 27.039829978747346,
    "end_time": 27.56560445055632,
    "table_confidence_percent": 89.3,
    "prominence": 326.46315540293097,
    "width_time": 0.5257744718089761,
    "width_samples": 98.0,
    "height": 326.3947681628979,
    "snr": 3.7658005485924186,
    "peak_area": 77.34203723196845,
    "prominence_threshold": 103.13911448862717,
    "width_threshold_samples": 4,
    "height_threshold": 168.55920951891525,
    "snr_threshold": 0.4321257796970041,
    "area_threshold": 2.079154077708448,
    "prominence_percent_above_threshold": 216.52701016637974,
    "width_percent_above_threshold": 2350.0,
    "height_percent_above_threshold": 93.63805104121039,
    "snr_percent_above_threshold": 771.4593587156279,
    "area_percent_above_threshold": 3619.8800253039176,
    "feature_explanation": "This peak's prominence is 216.5% above threshold, width is 2350.0% above threshold, height is 93.6% above threshold, S/N is 771.5% above threshold, and area is 3619.9% above threshold.",
    "counterfactual_explanation": "If prominence were 216.5% lower, or width were 2350.0% lower, or height were 93.6% lower, or S/N were 771.5% lower, or area were 3619.9% lower, this peak would fail detection.",
    "hybrid_explanation": "prominence: 326.463 (216.5% above threshold), width: 98.000 (2350.0% above threshold), height: 326.395 (93.6% above threshold), S/N: 3.766 (771.5% above threshold), area: 77.342 (3619.9% above threshold).",
    "weakest_constraint_explanation": "The limiting factor is height, which is only 93.6% above its threshold.",
    "confidence": 0.893,
    "confidence_explanation": "Confidence is based on the weakest margin: 93.6% above threshold (lower means less robust)."
  },
  {
    "peak_id": "peak_26",
    "apex_time_table": 29.507750968871107,
    "apex_time_recomputed": 29.507750968871107,
    "start_time": 29.137562820352542,
    "end_time": 29.94231966495812,
    "table_confidence_percent": 98.9,
    "prominence": 292.38649337034144,
    "width_time": 0.8047568446055777,
    "width_samples": 150.0,
    "height": 292.73768627455877,
    "snr": 3.3322549553687875,
    "peak_area": 93.58676099146209,
    "prominence_threshold": 103.13911448862717,
    "width_threshold_samples": 4,
    "height_threshold": 168.55920951891525,
    "snr_threshold": 0.4321257796970041,
    "area_threshold": 2.079154077708448,
    "prominence_percent_above_threshold": 183.48749630052524,
    "width_percent_above_threshold": 3650.0,
    "height_percent_above_threshold": 73.6705381509923,
    "snr_percent_above_threshold": 671.1307938409234,
    "area_percent_above_threshold": 4401.194115185984,
    "feature_explanation": "This peak's prominence is 183.5% above threshold, width is 3650.0% above threshold, height is 73.7% above threshold, S/N is 671.1% above threshold, and area is 4401.2% above threshold.",
    "counterfactual_explanation": "If prominence were 183.5% lower, or width were 3650.0% lower, or height were 73.7% lower, or S/N were 671.1% lower, or area were 4401.2% lower, this peak would fail detection.",
    "hybrid_explanation": "prominence: 292.386 (183.5% above threshold), width: 150.000 (3650.0% above threshold), height: 292.738 (73.7% above threshold), S/N: 3.332 (671.1% above threshold), area: 93.587 (4401.2% above threshold).",
    "weakest_constraint_explanation": "The limiting factor is height, which is only 73.7% above its threshold.",
    "confidence": 0.9890000000000001,
    "confidence_explanation": "Confidence is based on the weakest margin: 73.7% above threshold (lower means less robust)."
  },
  {
    "peak_id": "peak_27",
    "apex_time_table": 31.626943992999124,
    "apex_time_recomputed": 31.626943992999124,
    "start_time": 31.573293536692084,
    "end_time": 31.669864358044755,
    "table_confidence_percent": 61.7,
    "prominence": 343.1144945405627,
    "width_time": 0.09657082135267103,
    "width_samples": 18.0,
    "height": 343.0062285621354,
    "snr": 5.599644154061106,
    "peak_area": 14.455793816408795,
    "prominence_threshold": 103.13911448862717,
    "width_threshold_samples": 4,
    "height_threshold": 168.55920951891525,
    "snr_threshold": 0.4321257796970041,
    "area_threshold": 2.079154077708448,
    "prominence_percent_above_threshold": 232.6715536019042,
    "width_percent_above_threshold": 350.0,
    "height_percent_above_threshold": 103.4930215567036,
    "snr_percent_above_threshold": 1195.8366330255596,
    "area_percent_above_threshold": 595.2728502132624,
    "feature_explanation": "This peak's prominence is 232.7% above threshold, width is 350.0% above threshold, height is 103.5% above threshold, S/N is 1195.8% above threshold, and area is 595.3% above threshold.",
    "counterfactual_explanation": "If prominence were 232.7% lower, or width were 350.0% lower, or height were 103.5% lower, or S/N were 1195.8% lower, or area were 595.3% lower, this peak would fail detection.",
    "hybrid_explanation": "prominence: 343.114 (232.7% above threshold), width: 18.000 (350.0% above threshold), height: 343.006 (103.5% above threshold), S/N: 5.600 (1195.8% above threshold), area: 14.456 (595.3% above threshold).",
    "weakest_constraint_explanation": "The limiting factor is height, which is only 103.5% above its threshold.",
    "confidence": 0.617,
    "confidence_explanation": "Confidence is based on the weakest margin: 103.5% above threshold (lower means less robust)."
  },
  {
    "peak_id": "peak_28",
    "apex_time_table": 32.83407925990749,
    "apex_time_recomputed": 32.83407925990749,
    "start_time": 32.74287348418552,
    "end_time": 32.91455494436804,
    "table_confidence_percent": 30.1,
    "prominence": 183.63582376576008,
    "width_time": 0.17168146018251917,
    "width_samples": 32.0,
    "height": 185.41966999617182,
    "snr": 3.8269780923413155,
    "peak_area": 13.99368255548221,
    "prominence_threshold": 103.13911448862717,
    "width_threshold_samples": 4,
    "height_threshold": 168.55920951891525,
    "snr_threshold": 0.4321257796970041,
    "area_threshold": 2.079154077708448,
    "prominence_percent_above_threshold": 78.04673297443235,
    "width_percent_above_threshold": 700.0,
    "height_percent_above_threshold": 10.002693133990126,
    "snr_percent_above_threshold": 785.616705169661,
    "area_percent_above_threshold": 573.0469235308153,
    "feature_explanation": "This peak's prominence is 78.0% above threshold, width is 700.0% above threshold, height is 10.0% above threshold, S/N is 785.6% above threshold, and area is 573.0% above threshold.",
    "counterfactual_explanation": "If prominence were 78.0% lower, or width were 700.0% lower, or height were 10.0% lower, or S/N were 785.6% lower, or area were 573.0% lower, this peak would fail detection.",
    "hybrid_explanation": "prominence: 183.636 (78.0% above threshold), width: 32.000 (700.0% above threshold), height: 185.420 (10.0% above threshold), S/N: 3.827 (785.6% above threshold), area: 13.994 (573.0% above threshold).",
    "weakest_constraint_explanation": "The limiting factor is height, which is only 10.0% above its threshold.",
    "confidence": 0.301,
    "confidence_explanation": "Confidence is based on the weakest margin: 10.0% above threshold (lower means less robust)."
  },
  {
    "peak_id": "peak_29",
    "apex_time_table": 34.06803975496937,
    "apex_time_recomputed": 34.06803975496937,
    "start_time": 33.79978747343418,
    "end_time": 34.32556194524315,
    "table_confidence_percent": 90.3,
    "prominence": 336.03009615334645,
    "width_time": 0.5257744718089725,
    "width_samples": 98.0,
    "height": 336.11788609497404,
    "snr": 3.6399580897918793,
    "peak_area": 77.44121596070316,
    "prominence_threshold": 103.13911448862717,
    "width_threshold_samples": 4,
    "height_threshold": 168.55920951891525,
    "snr_threshold": 0.4321257796970041,
    "area_threshold": 2.079154077708448,
    "prominence_percent_above_threshold": 225.80277406822168,
    "width_percent_above_threshold": 2350.0,
    "height_percent_above_threshold": 99.40642048232661,
    "snr_percent_above_threshold": 742.3376389032212,
    "area_percent_above_threshold": 3624.650173403957,
    "feature_explanation": "This peak's prominence is 225.8% above threshold, width is 2350.0% above threshold, height is 99.4% above threshold, S/N is 742.3% above threshold, and area is 3624.7% above threshold.",
    "counterfactual_explanation": "If prominence were 225.8% lower, or width were 2350.0% lower, or height were 99.4% lower, or S/N were 742.3% lower, or area were 3624.7% lower, this peak would fail detection.",
    "hybrid_explanation": "prominence: 336.030 (225.8% above threshold), width: 98.000 (2350.0% above threshold), height: 336.118 (99.4% above threshold), S/N: 3.640 (742.3% above threshold), area: 77.441 (3624.7% above threshold).",
    "weakest_constraint_explanation": "The limiting factor is height, which is only 99.4% above its threshold.",
    "confidence": 0.903,
    "confidence_explanation": "Confidence is based on the weakest margin: 99.4% above threshold (lower means less robust)."
  },
  {
    "peak_id": "peak_30",
    "apex_time_table": 35.13568383547943,
    "apex_time_recomputed": 35.13568383547943,
    "start_time": 35.03374796849606,
    "end_time": 35.23761970246281,
    "table_confidence_percent": 5.0,
    "prominence": 25.769,
    "width_time": 0.20387173396674996,
    "width_samples": 38.0,
    "height": 25.769,
    "snr": 0.818,
    "peak_area": 1.453,
    "prominence_threshold": 103.13911448862717,
    "width_threshold_samples": 4,
    "height_threshold": 168.55920951891525,
    "snr_threshold": 0.4321257796970041,
    "area_threshold": 2.079154077708448,
    "prominence_percent_above_threshold": -75.01529838823518,
    "width_percent_above_threshold": 850.0,
    "height_percent_above_threshold": -84.71219693450907,
    "snr_percent_above_threshold": 89.29673683749239,
    "area_percent_above_threshold": -30.11580932946381,
    "feature_explanation": "This peak's prominence is 75.0% below threshold, width is 850.0% above threshold, height is 84.7% below threshold, S/N is 89.3% above threshold, and area is 30.1% below threshold.",
    "counterfactual_explanation": "If prominence were 75.0% lower, or width were 850.0% lower, or height were 84.7% lower, or S/N were 89.3% lower, or area were 30.1% lower, this peak would fail detection.",
    "hybrid_explanation": "prominence: 25.769 (-75.0% above threshold), width: 38.000 (850.0% above threshold), height: 25.769 (-84.7% above threshold), S/N: 0.818 (89.3% above threshold), area: 1.453 (-30.1% above threshold).",
    "weakest_constraint_explanation": "The limiting factor is height, which is only -84.7% above its threshold.",
    "confidence": 0.05,
    "confidence_explanation": "Confidence is based on the weakest margin: -84.7% above threshold (lower means less robust)."
  },
  {
    "peak_id": "peak_31",
    "apex_time_table": 35.91361545193149,
    "apex_time_recomputed": 35.91361545193149,
    "start_time": 35.7902194024253,
    "end_time": 35.99409113639205,
    "table_confidence_percent": 31.8,
    "prominence": 183.06535041579644,
    "width_time": 0.20387173396674996,
    "width_samples": 38.0,
    "height": 183.9769222449223,
    "snr": 4.0035623027034815,
    "peak_area": 12.754206557487736,
    "prominence_threshold": 103.13911448862717,
    "width_threshold_samples": 4,
    "height_threshold": 168.55920951891525,
    "snr_threshold": 0.4321257796970041,
    "area_threshold": 2.079154077708448,
    "prominence_percent_above_threshold": 77.49362239868996,
    "width_percent_above_threshold": 850.0,
    "height_percent_above_threshold": 9.14676378111331,
    "snr_percent_above_threshold": 826.4807819405453,
    "area_percent_above_threshold": 513.4324865209056,
    "feature_explanation": "This peak's prominence is 77.5% above threshold, width is 850.0% above threshold, height is 9.1% above threshold, S/N is 826.5% above threshold, and area is 513.4% above threshold.",
    "counterfactual_explanation": "If prominence were 77.5% lower, or width were 850.0% lower, or height were 9.1% lower, or S/N were 826.5% lower, or area were 513.4% lower, this peak would fail detection.",
    "hybrid_explanation": "prominence: 183.065 (77.5% above threshold), width: 38.000 (850.0% above threshold), height: 183.977 (9.1% above threshold), S/N: 4.004 (826.5% above threshold), area: 12.754 (513.4% above threshold).",
    "weakest_constraint_explanation": "The limiting factor is height, which is only 9.1% above its threshold.",
    "confidence": 0.318,
    "confidence_explanation": "Confidence is based on the weakest margin: 9.1% above threshold (lower means less robust)."
  },
  {
    "peak_id": "peak_32",
    "apex_time_table": 36.92760907613452,
    "apex_time_recomputed": 36.92760907613452,
    "start_time": 36.85249843730466,
    "end_time": 37.00808476059508,
    "table_confidence_percent": 55.8,
    "prominence": 343.1474042652418,
    "width_time": 0.15558632329042155,
    "width_samples": 29.0,
    "height": 344.7498215122932,
    "snr": 3.3309011414621468,
    "peak_area": 22.701448822722543,
    "prominence_threshold": 103.13911448862717,
    "width_threshold_samples": 4,
    "height_threshold": 168.55920951891525,
    "snr_threshold": 0.4321257796970041,
    "area_threshold": 2.079154077708448,
    "prominence_percent_above_threshold": 232.70346169500957,
    "width_percent_above_threshold": 625.0,
    "height_percent_above_threshold": 104.5274313377735,
    "snr_percent_above_threshold": 670.8175022091235,
    "area_percent_above_threshold": 991.8598609941923,
    "feature_explanation": "This peak's prominence is 232.7% above threshold, width is 625.0% above threshold, height is 104.5% above threshold, S/N is 670.8% above threshold, and area is 991.9% above threshold.",
    "counterfactual_explanation": "If prominence were 232.7% lower, or width were 625.0% lower, or height were 104.5% lower, or S/N were 670.8% lower, or area were 991.9% lower, this peak would fail detection.",
    "hybrid_explanation": "prominence: 343.147 (232.7% above threshold), width: 29.000 (625.0% above threshold), height: 344.750 (104.5% above threshold), S/N: 3.331 (670.8% above threshold), area: 22.701 (991.9% above threshold).",
    "weakest_constraint_explanation": "The limiting factor is height, which is only 104.5% above its threshold.",
    "confidence": 0.5579999999999999,
    "confidence_explanation": "Confidence is based on the weakest margin: 104.5% above threshold (lower means less robust)."
  },
  {
    "peak_id": "peak_33",
    "apex_time_table": 38.10791911488936,
    "apex_time_recomputed": 38.10791911488936,
    "start_time": 37.96842792849106,
    "end_time": 38.258140392549066,
    "table_confidence_percent": 85.5,
    "prominence": 414.5449904021882,
    "width_time": 0.289712464058006,
    "width_samples": 54.0,
    "height": 414.2295661307327,
    "snr": 3.827196947677816,
    "peak_area": 52.5050827093813,
    "prominence_threshold": 103.13911448862717,
    "width_threshold_samples": 4,
    "height_threshold": 168.55920951891525,
    "snr_threshold": 0.4321257796970041,
    "area_threshold": 2.079154077708448,
    "prominence_percent_above_threshold": 301.9280100062317,
    "width_percent_above_threshold": 1250.0,
    "height_percent_above_threshold": 145.74721684622577,
    "snr_percent_above_threshold": 785.6673513812002,
    "area_percent_above_threshold": 2425.3098494388682,
    "feature_explanation": "This peak's prominence is 301.9% above threshold, width is 1250.0% above threshold, height is 145.7% above threshold, S/N is 785.7% above threshold, and area is 2425.3% above threshold.",
    "counterfactual_explanation": "If prominence were 301.9% lower, or width were 1250.0% lower, or height were 145.7% lower, or S/N were 785.7% lower, or area were 2425.3% lower, this peak would fail detection.",
    "hybrid_explanation": "prominence: 414.545 (301.9% above threshold), width: 54.000 (1250.0% above threshold), height: 414.230 (145.7% above threshold), S/N: 3.827 (785.7% above threshold), area: 52.505 (2425.3% above threshold).",
    "weakest_constraint_explanation": "The limiting factor is height, which is only 145.7% above its threshold.",
    "confidence": 0.855,
    "confidence_explanation": "Confidence is based on the weakest margin: 145.7% above threshold (lower means less robust)."
  },
  {
    "peak_id": "peak_34",
    "apex_time_table": 38.62296349543693,
    "apex_time_recomputed": 38.62296349543693,
    "start_time": 38.56931303912989,
    "end_time": 38.68197899737467,
    "table_confidence_percent": 44.8,
    "prominence": 265.4416797327736,
    "width_time": 0.11266595824478287,
    "width_samples": 21.0,
    "height": 274.3119350509562,
    "snr": 4.603797290037662,
    "peak_area": 12.266719167735861,
    "prominence_threshold": 103.13911448862717,
    "width_threshold_samples": 4,
    "height_threshold": 168.55920951891525,
    "snr_threshold": 0.4321257796970041,
    "area_threshold": 2.079154077708448,
    "prominence_percent_above_threshold": 157.36276780041874,
    "width_percent_above_threshold": 425.0,
    "height_percent_above_threshold": 62.73921539728963,
    "snr_percent_above_threshold": 965.383623551858,
    "area_percent_above_threshold": 489.98605727458624,
    "feature_explanation": "This peak's prominence is 157.4% above threshold, width is 425.0% above threshold, height is 62.7% above threshold, S/N is 965.4% above threshold, and area is 490.0% above threshold.",
    "counterfactual_explanation": "If prominence were 157.4% lower, or width were 425.0% lower, or height were 62.7% lower, or S/N were 965.4% lower, or area were 490.0% lower, this peak would fail detection.",
    "hybrid_explanation": "prominence: 265.442 (157.4% above threshold), width: 21.000 (425.0% above threshold), height: 274.312 (62.7% above threshold), S/N: 4.604 (965.4% above threshold), area: 12.267 (490.0% above threshold).",
    "weakest_constraint_explanation": "The limiting factor is height, which is only 62.7% above its threshold.",
    "confidence": 0.44799999999999995,
    "confidence_explanation": "Confidence is based on the weakest margin: 62.7% above threshold (lower means less robust)."
  },
  {
    "peak_id": "peak_35",
    "apex_time_table": 40.23247718464808,
    "apex_time_recomputed": 40.23247718464808,
    "start_time": 40.13054131766471,
    "end_time": 40.33441305163145,
    "table_confidence_percent": 3.3,
    "prominence": 37.375,
    "width_time": 0.20387173396674285,
    "width_samples": 38.0,
    "height": 37.375,
    "snr": 0.463,
    "peak_area": 1.491,
    "prominence_threshold": 103.13911448862717,
    "width_threshold_samples": 4,
    "height_threshold": 168.55920951891525,
    "snr_threshold": 0.4321257796970041,
    "area_threshold": 2.079154077708448,
    "prominence_percent_above_threshold": -63.76253549847839,
    "width_percent_above_threshold": 850.0,
    "height_percent_above_threshold": -77.82678258478313,
    "snr_percent_above_threshold": 7.14473001926526,
    "area_percent_above_threshold": -28.288142952670707,
    "feature_explanation": "This peak's prominence is 63.8% below threshold, width is 850.0% above threshold, height is 77.8% below threshold, S/N is 7.1% above threshold, and area is 28.3% below threshold.",
    "counterfactual_explanation": "If prominence were 63.8% lower, or width were 850.0% lower, or height were 77.8% lower, or S/N were 7.1% lower, or area were 28.3% lower, this peak would fail detection.",
    "hybrid_explanation": "prominence: 37.375 (-63.8% above threshold), width: 38.000 (850.0% above threshold), height: 37.375 (-77.8% above threshold), S/N: 0.463 (7.1% above threshold), area: 1.491 (-28.3% above threshold).",
    "weakest_constraint_explanation": "The limiting factor is height, which is only -77.8% above its threshold.",
    "confidence": 0.033,
    "confidence_explanation": "Confidence is based on the weakest margin: -77.8% above threshold (lower means less robust)."
  },
  {
    "peak_id": "peak_36",
    "apex_time_table": 40.881647705963246,
    "apex_time_recomputed": 40.881647705963246,
    "start_time": 40.82799724965621,
    "end_time": 40.92456807100888,
    "table_confidence_percent": 53.7,
    "prominence": 298.5992914388404,
    "width_time": 0.09657082135267103,
    "width_samples": 18.0,
    "height": 298.5288328758705,
    "snr": 5.574725499302559,
    "peak_area": 12.515856145598283,
    "prominence_threshold": 103.13911448862717,
    "width_threshold_samples": 4,
    "height_threshold": 168.55920951891525,
    "snr_threshold": 0.4321257796970041,
    "area_threshold": 2.079154077708448,
    "prominence_percent_above_threshold": 189.5112033095514,
    "width_percent_above_threshold": 350.0,
    "height_percent_above_threshold": 77.10621313893287,
    "snr_percent_above_threshold": 1190.0701048688693,
    "area_percent_above_threshold": 501.9686698444546,
    "feature_explanation": "This peak's prominence is 189.5% above threshold, width is 350.0% above threshold, height is 77.1% above threshold, S/N is 1190.1% above threshold, and area is 502.0% above threshold.",
    "counterfactual_explanation": "If prominence were 189.5% lower, or width were 350.0% lower, or height were 77.1% lower, or S/N were 1190.1% lower, or area were 502.0% lower, this peak would fail detection.",
    "hybrid_explanation": "prominence: 298.599 (189.5% above threshold), width: 18.000 (350.0% above threshold), height: 298.529 (77.1% above threshold), S/N: 5.575 (1190.1% above threshold), area: 12.516 (502.0% above threshold).",
    "weakest_constraint_explanation": "The limiting factor is height, which is only 77.1% above its threshold.",
    "confidence": 0.537,
    "confidence_explanation": "Confidence is based on the weakest margin: 77.1% above threshold (lower means less robust)."
  },
  {
    "peak_id": "peak_37",
    "apex_time_table": 41.552278409801225,
    "apex_time_recomputed": 41.6542142767846,
    "start_time": 41.45034254281785,
    "end_time": 41.6542142767846,
    "table_confidence_percent": 3.8,
    "prominence": 23.311,
    "width_time": 0.20387173396674996,
    "width_samples": 38.0,
    "height": 23.311,
    "snr": 0.583,
    "peak_area": 0.272,
    "prominence_threshold": 103.13911448862717,
    "width_threshold_samples": 4,
    "height_threshold": 168.55920951891525,
    "snr_threshold": 0.4321257796970041,
    "area_threshold": 2.079154077708448,
    "prominence_percent_above_threshold": -77.3984873579941,
    "width_percent_above_threshold": 850.0,
    "height_percent_above_threshold": -86.17043822966902,
    "snr_percent_above_threshold": 34.91442246486315,
    "area_percent_above_threshold": -86.91775646084938,
    "feature_explanation": "This peak's prominence is 77.4% below threshold, width is 850.0% above threshold, height is 86.2% below threshold, S/N is 34.9% above threshold, and area is 86.9% below threshold.",
    "counterfactual_explanation": "If prominence were 77.4% lower, or width were 850.0% lower, or height were 86.2% lower, or S/N were 34.9% lower, or area were 86.9% lower, this peak would fail detection.",
    "hybrid_explanation": "prominence: 23.311 (-77.4% above threshold), width: 38.000 (850.0% above threshold), height: 23.311 (-86.2% above threshold), S/N: 0.583 (34.9% above threshold), area: 0.272 (-86.9% above threshold).",
    "weakest_constraint_explanation": "The limiting factor is area, which is only -86.9% above its threshold.",
    "confidence": 0.038,
    "confidence_explanation": "Confidence is based on the weakest margin: -86.9% above threshold (lower means less robust)."
  },
  {
    "peak_id": "peak_38",
    "apex_time_table": 42.25509938742343,
    "apex_time_recomputed": 42.25509938742343,
    "start_time": 42.15852856607076,
    "end_time": 42.3463051631454,
    "table_confidence_percent": 36.7,
    "prominence": 204.41290123870866,
    "width_time": 0.18777659707464522,
    "width_samples": 35.0,
    "height": 206.39947405145261,
    "snr": 4.196578605143176,
    "peak_area": 15.789295452776145,
    "prominence_threshold": 103.13911448862717,
    "width_threshold_samples": 4,
    "height_threshold": 168.55920951891525,
    "snr_threshold": 0.4321257796970041,
    "area_threshold": 2.079154077708448,
    "prominence_percent_above_threshold": 98.19144487734441,
    "width_percent_above_threshold": 775.0,
    "height_percent_above_threshold": 22.449241806803226,
    "snr_percent_above_threshold": 871.1474765716854,
    "area_percent_above_threshold": 659.4095897971356,
    "feature_explanation": "This peak's prominence is 98.2% above threshold, width is 775.0% above threshold, height is 22.4% above threshold, S/N is 871.1% above threshold, and area is 659.4% above threshold.",
    "counterfactual_explanation": "If prominence were 98.2% lower, or width were 775.0% lower, or height were 22.4% lower, or S/N were 871.1% lower, or area were 659.4% lower, this peak would fail detection.",
    "hybrid_explanation": "prominence: 204.413 (98.2% above threshold), width: 35.000 (775.0% above threshold), height: 206.399 (22.4% above threshold), S/N: 4.197 (871.1% above threshold), area: 15.789 (659.4% above threshold).",
    "weakest_constraint_explanation": "The limiting factor is height, which is only 22.4% above its threshold.",
    "confidence": 0.36700000000000005,
    "confidence_explanation": "Confidence is based on the weakest margin: 22.4% above threshold (lower means less robust)."
  }
]